Workbook

Sheet Disclaimer
C3: This excel document (“Financial Model”) has been prepared by Monte Cristo Advisory for [°] in order to compute and present cash flow projections of its solar projects in France, [°]. This Financial Model has not been audited and no representation, warranty, or undertaking (express or implied) is made and no responsibility is taken or accepted by Monte Cristo Advisory as to the adequacy, accuracy, completeness or reasonableness of the Financial Model and Monte Cristo Advisory excludes all liability thereof. In particular, no responsibility is taken or accepted by Monte Cristo Advisory and all liability is excluded by Monte Cristo Advisory for the calculations and the results comprised therein and the assumptions upon which such computations are based. In addition, the recipient receives and uses this Financial Model entirely at its own risk and, in the absence of express written consent by Monte Cristo Advisory, no responsibility is taken or accepted by Monte Cristo Advisory for any losses which may result therefrom, including whether as a direct or indirect consequence of a computer virus or otherwise. The recipient of this financial model should make (and will be deemed to have made) its own review and due diligence in respect of the Financial Model. In the absence of express written consent, this model remains the property of Monte Cristo Advisory.

Sheet Dashboard
D3: MONTE CRISTO ADVISORY | M3: Calage | N3: Check Vehicle | O3: Master check
M4: =Calage -> #REF! | N4: =#REF! -> #REF! | O4: =Master_check -> #REF!
C7: 1 | D7: DASHBOARD
D11: USES & SOURCES @ COD | P11: PERIMETER
X12: =IF(INDEX(#REF!,,#REF!)=1,"n/a",INDEX(#REF!,,INDEX(#REF!,,ref_Vehicle))) -> #REF!
D13: Uses | J13: Sources | P13: Capacity, of which : | R13: kWc | S13: =INDEX(#REF!,,ref_Vehicle) -> #REF!
D14: =#REF!&", of which :" -> #REF! | F14: k€ | G14: {=SUM((#REF!=ref_Vehicle)*(IF(Phase<>9,Phase_Asset=Phase,1))*(#REF!)*(#REF!<>0))} -> #REF! | H14: =IF($G$32=0,0,G14/$G$32) -> #REF! | J14: Share capital | L14: k€ | M14: =#REF! -> #REF! | N14: =IF($M$32=0,0,M14/$M$32) -> #REF! | P14: per detention | R14: kWc | S14: =INDEX(#REF!,,ref_Vehicle)*#REF! -> #REF!
D15: {=#REF!} -> #REF! | F15: k€ | G15: {=_xlfn.LET(_xlpm.calcul,(#REF!=ref_Vehicle)*(IF(Phase<>9,Phase_Asset=Phase,1))*(#REF!<>0),IF(SUM(_xlpm.calcul*(#REF!))=0,0,SUM(_xlpm.calcul*(#REF!))/SUM(_xlpm.calcul*(#REF!))))*G$14} -> #NAME? | H15: =IF($G$32=0,0,G15/$G$32) -> #REF! | J15: SHL from Holdco | L15: k€ | M15: =IF(#REF!=TRUE(),SUM(#REF!,#REF!,#REF!,#REF!,#REF!,#REF!,#REF!,#REF!,-M16),SUM(#REF!,#REF!,#REF!,#REF!,#REF!,#REF!,#REF!,#REF!)) -> #REF! | N15: =IF($M$32=0,0,M15/$M$32) -> #REF!
D16: #REF! | F16: k€ | G16: {=_xlfn.LET(_xlpm.calcul,(#REF!=ref_Vehicle)*(IF(Phase<>9,Phase_Asset=Phase,1))*(#REF!<>0),IF(SUM(_xlpm.calcul*(#REF!))=0,0,SUM(_xlpm.calcul*(#REF!))/SUM(_xlpm.calcul*(#REF!))))*G$14} -> #NAME? | H16: =IF($G$32=0,0,G16/$G$32) -> #REF! | J16: Crowdfunding debt | L16: k€ | M16: =#REF! -> #REF! | N16: =IF($M$32=0,0,M16/$M$32) -> #REF! | P16: Construction costs | R16: k€ | S16: =INDEX(#REF!,,ref_Vehicle) -> #REF! | X16: =IF(INDEX(#REF!,,#REF!)=1,"n/a",INDEX(#REF!,,ref_Vehicle)) -> #REF!
D17: #REF! | F17: k€ | G17: {=_xlfn.LET(_xlpm.calcul,(#REF!=ref_Vehicle)*(IF(Phase<>9,Phase_Asset=Phase,1))*(#REF!<>0),IF(SUM(_xlpm.calcul*(#REF!))=0,0,SUM(_xlpm.calcul*(#REF!))/SUM(_xlpm.calcul*(#REF!))))*G$14} -> #NAME? | H17: =IF($G$32=0,0,G17/$G$32) -> #REF! | J17: Senior facility | L17: k€ | M17: =SUM(#REF!,#REF!,#REF!,#REF!,#REF!,#REF!,#REF!,,#REF!) -> #REF! | N17: =IF($M$32=0,0,M17/($M$32)) -> #REF! | P17: CAPEX per kWc | R17: € / Wc | S17: =IF(S13>0,S16/S13,0) -> #REF!
D18: #REF! | F18: k€ | G18: {=_xlfn.LET(_xlpm.calcul,(#REF!=ref_Vehicle)*(IF(Phase<>9,Phase_Asset=Phase,1))*(#REF!<>0),IF(SUM(_xlpm.calcul*(#REF!))=0,0,SUM(_xlpm.calcul*(#REF!))/SUM(_xlpm.calcul*(#REF!))))*G$14} -> #NAME? | H18: =IF($G$32=0,0,G18/$G$32) -> #REF! | J18: Pre-hedge gain | L18: k€ | M18: =MAX(-SUM(#REF!),0) -> #REF! | N18: =IFERROR(M18/$M$32,0) -> 0 | P18: Annual production | R18: MWh / year | S18: =INDEX(#REF!,,ref_Vehicle) -> #REF! | X18: =#REF! -> #REF!
D19: #REF! | F19: k€ | G19: {=_xlfn.LET(_xlpm.calcul,(#REF!=ref_Vehicle)*(IF(Phase<>9,Phase_Asset=Phase,1))*(#REF!<>0),IF(SUM(_xlpm.calcul*(#REF!))=0,0,SUM(_xlpm.calcul*(#REF!))/SUM(_xlpm.calcul*(#REF!))))*G$14} -> #NAME? | H19: =IF($G$32=0,0,G19/$G$32) -> #REF!
D20: #REF! | F20: k€ | G20: {=_xlfn.LET(_xlpm.calcul,(#REF!=ref_Vehicle)*(IF(Phase<>9,Phase_Asset=Phase,1))*(#REF!<>0),IF(SUM(_xlpm.calcul*(#REF!))=0,0,SUM(_xlpm.calcul*(#REF!))/SUM(_xlpm.calcul*(#REF!))))*G$14} -> #NAME? | H20: =IF($G$32=0,0,G20/$G$32) -> #REF! | P20: Last COD | R20: date | S20: =INDEX(#REF!,,ref_Vehicle) -> #REF!
D21: #REF! | F21: k€ | G21: {=_xlfn.LET(_xlpm.calcul,(#REF!=ref_Vehicle)*(IF(Phase<>9,Phase_Asset=Phase,1))*(#REF!<>0),IF(SUM(_xlpm.calcul*(#REF!))=0,0,SUM(_xlpm.calcul*(#REF!))/SUM(_xlpm.calcul*(#REF!))))*G$14} -> #NAME? | H21: =IF($G$32=0,0,G21/$G$32) -> #REF! | P21: Average P90 | R21: hours | S21: =INDEX(#REF!,,ref_Vehicle) -> #REF!
D22: #REF! | F22: k€ | G22: {=_xlfn.LET(_xlpm.calcul,(#REF!=ref_Vehicle)*(IF(Phase<>9,Phase_Asset=Phase,1))*(#REF!<>0),IF(SUM(_xlpm.calcul*(#REF!))=0,0,SUM(_xlpm.calcul*(#REF!))/SUM(_xlpm.calcul*(#REF!))))*G$14} -> #NAME? | H22: =IF($G$32=0,0,G22/$G$32) -> #REF! | P22: Average P50 | R22: hours | S22: =INDEX(#REF!,,ref_Vehicle) -> #REF!
D23: #REF! | F23: k€ | G23: {=_xlfn.LET(_xlpm.calcul,(#REF!=ref_Vehicle)*(IF(Phase<>9,Phase_Asset=Phase,1))*(#REF!<>0),IF(SUM(_xlpm.calcul*(#REF!))=0,0,SUM(_xlpm.calcul*(#REF!))/SUM(_xlpm.calcul*(#REF!))))*G$14} -> #NAME? | H23: =IF($G$32=0,0,G23/$G$32) -> #REF! | P23: Average Tariff | R23: €/MWh | S23: =INDEX(#REF!,,ref_Vehicle) -> #REF! | V23: Vehicle(s) in perimeter, of which : | W23: # | X23: =INDEX(#REF!,,ref_Vehicle) -> #REF!
D24: #REF! | F24: k€ | G24: {=_xlfn.LET(_xlpm.calcul,(#REF!=ref_Vehicle)*(IF(Phase<>9,Phase_Asset=Phase,1))*(#REF!<>0),IF(SUM(_xlpm.calcul*(#REF!))=0,0,SUM(_xlpm.calcul*(#REF!))/SUM(_xlpm.calcul*(#REF!))))*G$14} -> #NAME? | H24: =IF($G$32=0,0,G24/$G$32) -> #REF! | P24: =#REF! -> #REF! | R24: % | S24: =INDEX(#REF!,,ref_Vehicle) -> #REF! | V24: ="directly held by "&X18 -> #REF! | W24: # | X24: =COUNTIF(#REF!,ref_Vehicle) -> #REF!
D25: #REF! | F25: k€ | G25: {=_xlfn.LET(_xlpm.calcul,(#REF!=ref_Vehicle)*(IF(Phase<>9,Phase_Asset=Phase,1))*(#REF!<>0),IF(SUM(_xlpm.calcul*(#REF!))=0,0,SUM(_xlpm.calcul*(#REF!))/SUM(_xlpm.calcul*(#REF!))))*G$14} -> #NAME? | H25: =IF($G$32=0,0,G25/$G$32) -> #REF! | P25: =#REF! -> #REF! | R25: % | S25: =INDEX(#REF!,,ref_Vehicle) -> #REF!
D26: =#REF! -> #REF! | F26: k€ | G26: {=_xlfn.LET(_xlpm.calcul,(#REF!=ref_Vehicle)*(IF(Phase<>9,Phase_Asset=Phase,1))*(#REF!<>0),IF(SUM(_xlpm.calcul*(#REF!))=0,0,SUM(_xlpm.calcul*(#REF!))/SUM(_xlpm.calcul*(#REF!))))*G$14} -> #NAME? | H26: =IF($G$32=0,0,G26/$G$32) -> #REF! | V26: Asset(s) in vehicle(s) | W26: # | X26: =INDEX(#REF!,,ref_Vehicle) -> #REF!
D27: =#REF! -> #REF! | F27: k€ | G27: =#REF! -> #REF! | H27: =IF($G$32=0,0,G27/$G$32) -> #REF! | V27: Asset(s) in senior facility permiter | W27: # | X27: =INDEX(#REF!,,ref_Vehicle) -> #REF!
D28: =#REF! -> #REF! | F28: k€ | G28: =#REF! -> #REF! | H28: =IF($G$32=0,0,G28/$G$32) -> #REF!
D29: =#REF! -> #REF! | F29: k€ | G29: =#REF!-MIN(#REF!,0) -> #REF! | H29: =IF($G$32=0,0,G29/$G$32) -> #REF!
D30: =#REF! -> #REF! | F30: k€ | G30: =#REF! -> #REF! | H30: =IF($G$32=0,0,G30/$G$32) -> #REF!
D32: =#REF! -> #REF! | F32: k€ | G32: =SUM(G14,G27:G30) -> #REF! | H32: =IF(G32=0,0,G32/$G$32) -> #REF! | J32: =#REF! -> #REF! | L32: k€ | M32: =SUM(M14:M28) -> #REF! | N32: =IF(M32=0,0,M32/$G$32) -> #REF!
D38: FACILITIES | J38: RATIOS - LENDERS
D40: Senior facility, of which | F40: k€ | G40: =M17 -> #REF! | J40: =#REF! -> #REF! | L40: % | M40: =#REF! -> #REF!
D41: Phase 1 | F41: k€ | G41: =#REF! -> #REF! | J41: Gearing | L41: % | M41: =N17 -> #REF!
D42: Phase 2 | F42: k€ | G42: =#REF! -> #REF! | J42: Min HDSCR 12 months | L42: ratio | M42: =#REF! -> #REF!
D43: Phase 3 | F43: k€ | G43: =#REF! -> #REF! | J43: Avg HDSCR 12 months | L43: ratio | M43: =#REF! -> #REF!
D44: Phase 4 | F44: k€ | G44: =#REF! -> #REF! | J44: LLCR | L44: ratio | M44: =#REF! -> #REF!
D45: Phase 5 | F45: k€ | G45: =#REF! -> #REF! | J45: PLCR | L45: ratio | M45: =#REF! -> #REF!
D46: Phase 6 | F46: k€ | G46: =#REF! -> #REF! | J46: =AG137 -> Shortfall senior facility | L46: k€ | M46: =#REF! -> #REF!
D47: Phase 7 | F47: k€ | G47: =#REF! -> #REF!
D48: Phase 8 | F48: k€ | G48: =#REF! -> #REF! | J48: MERCHANT
D50: EBL | F50: k€ | G50: =#REF! -> #REF! | J50: Merchant debt | L50: k€ | M50: =IF(scenario=1,SUMPRODUCT(#REF!,#REF!)+SUMPRODUCT(#REF!,#REF!)+SUMPRODUCT(#REF!,#REF!)+SUMPRODUCT(#REF!,#REF!)+SUMPRODUCT(#REF!,#REF!)+SUMPRODUCT(#REF!,#REF!)+SUMPRODUCT(#REF!,#REF!)+SUMPRODUCT(#REF!,#REF!),) -> 0
D51: DSRF | F51: k€ | G51: =#REF! -> #REF! | J51: Merchant debt / Senior facility | L51: % | M51: =IF(AND(#REF!,$G$40>0,scenario=1),M50/$G$40,) -> #REF!
D52: CRTVA | F52: k€ | G52: =#REF! -> #REF! | J52: MDRA | L52: k€ | M52: =IF(scenario=1,#REF!*#REF!,) -> 0
J53: MDRA / Senior facility | L53: % | M53: =IF(AND(#REF!,$G$40>0,scenario=1),M52/$G$40,) -> #REF!
D54: Consolidation date | F54: date | G54: =IF(Phase=9,#REF!+1,#REF!) -> #REF! | J54: Part of merchant debt not covered by automatic MDRA & Cash sweep | L54: % | M54: =IF(scenario=1,(M50-G58-M52)/M17,) -> 0
D55: Senior facility repayment date - base case | F55: date | G55: =IF(#REF!,#REF!,0) -> #REF! | J55: MDRA funding start | L55: =#REF! -> #REF! | M55: =#REF! -> #REF!
D56: Duration | F56: years | G56: =YEARFRAC(G54,G55,1) -> #REF! | J56: MDRA last funding date | L56: =#REF! -> #REF! | M56: =#REF! -> #REF!
J57: Date Cible de Provisionnement | L57: =#REF! -> #REF! | M57: =+#REF! -> #REF!
D58: Cash sweep amount | F58: k€ | G58: =#REF! -> #REF!
J59: RATIOS - SPONSOR
J60: =#REF! -> #REF! | L60: % | M60: =#REF! -> #REF!
J61: ="Cash trap - "&#REF! -> #REF! | L61: k€ | M61: =#REF! -> #REF!
J62: Cash trap all perimeter | L62: k€ | M62: =SUM(#REF!) -> #REF!
J63: =#REF! -> #REF! | L63: k€ | M63: =#REF! -> #REF!
J64: NPV per Wc | L64: €/Wc | M64: =IF(S13=0,0,M63/S13) -> #REF!
J65: NPV sponsor, per detention @ 2025 | L65: k€ | M65: =#REF! -> #REF!
J66: NPV per Wc | L66: €/Wc | M66: =IF(S14=0,0,M65/S14) -> #REF!
D90: CHARTS
D135: SENSITIVES | AB135: Check | AC135: =IF(sensi=1,INDEX(AC140:AC164,$I$139,)=AC139,"n/a") -> n/a | AD135: =IF(sensi=1,INDEX(AD140:AD164,$I$139,)=AD139,"n/a") -> n/a | AE135: =IF(sensi=1,INDEX(AE140:AE164,$I$139,)=AE139,"n/a") -> n/a | AF135: =IF(sensi=1,INDEX(AF140:AF164,$I$139,)=AF139,"n/a") -> n/a | AG135: =IF(sensi=1,INDEX(AG140:AG164,$I$139,)=AG139,"n/a") -> n/a
A137: DASHBOARD_SENSITIVITY | D137: Sensitives mode | F137: list | G137: 2 | J137: Scenario | M137: Inflation | N137: Yield | O137: Availability | P137: Degradation | Q137: OPEX | R137: [ + ] | S137: Scenario market price | T137: Market price (excl. 0 €/MWh) | U137: EURIBOR | V137: MDRA sweep activation | W137: MDRA sweep prorata activation | X137: MDRA liberation date (last fundate date if empty) | Y137: Asset life in lender scenario | Z137: Asset life of X% portfolio activation | AA137: Asset life of X% portfolio | AB137: Asset desactivation @CoD | AC137: DSCR Min | AD137: DSCR Avg | AE137: LLCR | AF137: Shortfall MDRA | AG137: Shortfall senior facility
A138: DASHBOARD_SWEEP_ACTIVATION | D138: MDRA sweep activation | F138: # | G138: 3 | M138: +/- % | N138: Variation % | O138: % | P138: % | Q138: Variation % | R138: [ + ] | S138: scenario | T138: € / MWh | U138: +/- % | V138: 1/0 | W138: 1/0 | X138: date | Y138: months | Z138: VRAI/FAUX | AA138: months | AB138: VRAI/FAUX | AC138: ratio | AD138: ratio | AE138: ratio | AF138: k€ | AG138: k€
A139: DASHBOARD_SWEEP_PRORATA_ACTIVATION | D139: MDRA sweep prorata activation | F139: # | G139: 4 | I139: 15 | M139: =INDEX(M140:M164,$I$139,) -> 0 | N139: =INDEX(N140:N164,$I$139,) -> 0 | O139: =INDEX(O140:O164,$I$139,) -> 0 | P139: =INDEX(P140:P164,$I$139,) -> 0 | Q139: =INDEX(Q140:Q164,$I$139,) -> 0 | R139: =INDEX(R140:R164,$I$139,) -> 0 | S139: =INDEX(S140:S164,$I$139,) -> 0 | T139: =INDEX(T140:T164,$I$139,) -> 0 | ... Y139: =INDEX(Y140:Y164,$I$139,) -> 0 | Z139: {=INDEX(Z140:Z164,$I$139,)=TRUE()} -> 0 | AA139: =INDEX(AA140:AA164,$I$139,) -> 0 | AB139: {=INDEX(AB140:AB164,$I$139,)=TRUE()} -> 0 | AC139: =M42 -> #REF! | AD139: =M43 -> #REF! | AE139: =M44 -> #REF! | AF139: =#REF!-#REF! -> #REF! | AG139: =M46 -> #REF!
A140: DASHBOARD_SCENARIO | D140: Scenario | F140: # | G140: 5 | I140: 1 | J140: [ + ] | AG140: 0
A141: DASHBOARD_SCENARIO_LENDER | D141: Lender scenario | F141: # | G141: 6 | I141: 2 | J141: [ + ] | AG141: 0 | AH141: Calage MDRA sweep sizing
A142: DASHBOARD_SCENARIO_SPONSOR | D142: Sponsor scenario | F142: # | G142: 7 | I142: 3 | J142: [ + ] | AG142: 0 | AH142: =Calage_MDRA_sweep -> #NAME?
A143: DASHBOARD_CASHSWEEP | D143: Cash sweep | F143: # | G143: 8 | I143: 4 | J143: [ + ] | AG143: 0
A144: DASHBOARD_CASHSWEEP_ON | D144: Cash sweep on | F144: # | G144: 9 | I144: 5 | J144: [ + ]
A145: DASHBOARD_CASHSWEEP_OFF | D145: Cash sweep off | F145: # | G145: 10 | I145: 6 | J145: [ + ]
I146: 7 | J146: [ + ]
I147: 8 | J147: [ + ]
D148: STEP PLAN | I148: 9 | J148: [ + ]
C149: =C148+1 -> 1 | D149: Sizing tranche par tranche | I149: 10 | J149: [ + ]
C150: =C149+1 -> 2 | D150: Sizing top up | I150: 11 | J150: [ + ]
C151: =C150+1 -> 3 | D151: Sizing cash sweep | I151: 12 | J151: [ + ]
C152: =C151+1 -> 4 | D152: Sizing MDRA | I152: 13 | J152: [ + ]
I153: 14 | J153: [ + ]
I154: 15 | J154: [ + ]
I155: 16 | J155: [ + ]
I156: 17 | J156: [ + ]
I157: 18 | J157: [ + ]
I158: 19 | J158: [ + ]
I159: 20 | J159: [ + ]
I160: 21 | J160: [ + ]
I161: 22 | J161: [ + ]
I162: 23 | J162: [ + ]
I163: 24 | J163: [ + ]
I164: 25 | J164: [ + ]

Sheet ass_Model
B6: =1 -> 1 | C6: TIMELINE
C8: MODEL TIMELINE
A9: MODEL_TSTART | C9: Start | K9: date | M9: 45658
C10: Model periodicity | K10: month | M10: 12
A11: MODEL_TEND | C11: End | K11: date | M11: 59535
A13: MODEL_INFLATION_START | C13: Inflation start | K13: year | M13: 2026
B15: =B6+1 -> 2 | C15: TAXES
C17: VAT
C18: Rate | K18: % | M18: 0.2
C20: CVAE
C21: Added value thresholds
C22: Turnover threshold value | K22: k€ | M22: 7600
C23: Percentage of turnover if below threshold | K23: % | M23: 0.8
C24: Percentage of turnover if above threshold | K24: % | M24: 0.85
C26: Year | K26: year | M26: 2022 | N26: 2023 | O26: 2024 | P26: 2025 | Q26: 2026 | R26: 2027 | S26: 2028 | T26: 2029
C27: Turnover thresholds
C28: Turnover threshold 1 | K28: k€ | M28: 500 | N28: 500 | O28: 500 | P28: 500 | Q28: 500 | R28: 500 | S28: 500 | T28: 500
C29: Rate threshold 1 | K29: % | M29: 0 | N29: 0 | O29: 0 | P29: 0 | Q29: 0 | R29: 0 | S29: 0 | T29: 0
C31: Turnover threshold 2 | K31: k€ | M31: 3000 | N31: 3000 | O31: 3000 | P31: 3000 | Q31: 3000 | R31: 3000 | S31: 3000 | T31: 3000
C32: Added value coefficient de correction 2 | K32: % | M32: 0.00125 | N32: 0.00125 | O32: 0.00094 | P32: 0.00063 | Q32: 0.00094 | R32: 0.00094 | S32: 0.00063 | T32: 0.00031
C33: Added value to divide turnover | K33: k€ | M33: 2500 | N33: 2500 | O33: 2500 | P33: 2500 | Q33: 2500 | R33: 2500 | S33: 2500 | T33: 2500
C35: Turnover threshold 3 | K35: k€ | M35: 10000 | N35: 10000 | O35: 10000 | P35: 10000 | Q35: 10000 | R35: 10000 | S35: 10000 | T35: 10000
C36: Rate threshold 3 | K36: % | M36: 0.00125 | N36: 0.00125 | O36: 0.00094 | P36: 0.00063 | Q36: 0.00094 | R36: 0.00094 | S36: 0.00063 | T36: 0.00031
C37: Added value coefficient de correction 3 | K37: % | M37: 0.00225 | N37: 0.00225 | O37: 0.00169 | P37: 0.00113 | Q37: 0.00169 | R37: 0.00169 | S37: 0.00113 | T37: 0.00056
C38: Added value to divide turnover | K38: k€ | M38: 7000 | N38: 7000 | O38: 7000 | P38: 7000 | Q38: 7000 | R38: 7000 | S38: 7000 | T38: 7000
C40: Turnover threshold 4 | K40: k€ | M40: 50000 | N40: 50000 | O40: 50000 | P40: 50000 | Q40: 50000 | R40: 50000 | S40: 50000 | T40: 50000
C41: Rate threshold 4 | K41: % | M41: 0.0035 | N41: 0.0035 | O41: 0.00263 | P41: 0.00175 | Q41: 0.00263 | R41: 0.00263 | S41: 0.00175 | T41: 0.00087
C42: Added value coefficient de correction 4 | K42: % | M42: 0.00025 | N42: 0.00025 | O42: 0.00019 | P42: 0.00013 | Q42: 0.00019 | R42: 0.00019 | S42: 0.00013 | T42: 6e-05
... C46: Rate threshold 5 | K46: % | M46: 0.00375 | N46: 0.00375 | O46: 0.0028 | P46: 0.0019 | Q46: 0.0028 | R46: 0.0028 | S46: 0.0019 | T46: 0.0009
C48: Sponsor CVAE application | K48: VRAI / FAUX | M48: =TRUE() -> TRUE | N48: =TRUE() -> TRUE | O48: =TRUE() -> TRUE | P48: =TRUE() -> TRUE | Q48: =TRUE() -> TRUE | R48: =TRUE() -> TRUE | S48: =TRUE() -> TRUE | T48: =TRUE() -> TRUE
C49: Sponsor CVAE rate | K49: % | M49: 0.00375 | N49: 0.00375 | O49: 0.0028 | P49: 0.0019 | Q49: 0.0028 | R49: 0.0028 | S49: 0.0019 | T49: 0.0009
C51: Additional taxes and fees
C52: Tax for chamber of commerce and industry (CCI) | K52: % | M52: 0.0692 | N52: 0.0692 | O52: 0.0923 | P52: 0.1384 | Q52: 0.2768 | R52: 0.2768 | S52: 0.2768 | T52: 0.2768
C53: Tax management fees | K53: % | M53: 0
C55: CORPORATE INCOME TAX
C56: CIT rate | K56: % | M56: 0.25
C58: Tax loss carry forward limits
C59: Threshold for full utilisation of losses | K59: k€ | M59: 1000
C60: Proportion of taxable income | K60: % | M60: 0.5
C62: Related party loan ("RPL") interests deductibility
C63: Part of RPL interests subject to deductibility | K63: % | M63: 1
C65: Part of dividend subject to deductibility | K65: % | M65: 0.95
C67: Minimum duration of shares' detention for deductibility on disposals | K67: year | M67: 2
C68: Part of gain on disposal subject to CIT | K68: % | M68: 0.12
C70: Financing expenses deductibility
C71: Intragroup debt to equity ratio for reduced thresholds | K71: ratio | M71: 1.5
C72: Maximum interest expense for full deductibility if intragroup debt is below threshold | K72: k€ | M72: 3000
C73: Maximum interest expense as a percentage of EBITDA for full deductibility if intragroup debt is below threshold | K73: % | M73: 0.3
C74: Maximum interest expense for full deductibility if intragroup debt is above threshold | K74: k€ | M74: 1000
C75: Maximum interest expense as a percentage of EBITDA for full deductibility if intragroup debt is above threshold | K75: % | M75: 0.1
C76: Percentage of disallowed financing charges to be carried forward if under capitalised | K76: % | M76: 0.33333333
C78: Legal limit of SHL interest deductibility
C79: Rate Threshold | K79: % | M79: 0.0587
C81: LEGAL RESERVE
C82: Target balance | K82: % | M82: 0.1
C83: Net income allocation | K83: % | M83: 0.05
C85: CIT COTISATION
C86: CIT
C87: CA Threshold | K87: k€ | M87: 7630
C88: Taxable base reduction | K88: k€ | M88: 763
C89: CIT Cotisation | K89: % | M89: 0.033
C91: IFER
C92: Solar plants
C93: Long stop date COD | K93: date | M93: 44197
C94: Reduced tax rate duration | K94: year | M94: 20
C95: IFER prior long stop date | K95: k€ / MW / year | M95: 8.51
C96: IFER post long stop date - before year 20 | K96: k€ / MW / year | M96: 3.542
C97: IFER post long stop date - after year 20 | K97: k€ / MW / year | M97: 8.51
C99: Wind projects
C100: IFER | K100: k€ / MW / year | M100: 8.36
C102: Index | K102: list | M102: IPC
C103: Base year for indexation | K103: year | M103: 2025
B105: =B15+1 -> 3 | C105: CALAGE & FORMATTING
C107: Calage accuracy | K107: rounded | M107: 2
C108: Accuracy check | K108: rounded | M108: 2
C109: Max iteration | K109: number | M109: 60
B111: =+B105+1 -> 4 | C111: PHASE
C113: Phase | K113: # | M113: Phase 5
C114: ="Phase "&M114 -> Phase 1 | K114: # | M114: 1
C115: ="Phase "&M115 -> Phase 2 | K115: # | M115: 2
C116: ="Phase "&M116 -> Phase 3 | K116: # | M116: 3
C117: ="Phase "&M117 -> Phase 4 | K117: # | M117: 4
C118: ="Phase "&M118 -> Phase 5 | K118: # | M118: 5
C119: ="Phase "&M119 -> Phase 6 | K119: # | M119: 6
C120: ="Phase "&M120 -> Phase 7 | K120: # | M120: 7
C121: ="Phase "&M121 -> Phase 8 | K121: # | M121: 8
C122: All Phase | K122: # | M122: 9
B124: =+B111+1 -> 5 | C124: END

Sheet ass_Vehicle
A2: VEHICLE_NAME | C2: Vehicle name | K2: ### | M2: TopCo | N2: Holdco_1 | O2: Holdco_2 | P2: SPV_1 | Q2: SPV_2 | R2: SPV_3
C3: Vehicle activation flag | K3: VRAI / FAUX | M3: =AND(M4=TRUE(),M47=TRUE()) -> #REF! | N3: =AND(N4=TRUE(),N47=TRUE()) -> #REF! | O3: =AND(O4=TRUE(),O47=TRUE()) -> FALSE | P3: =AND(P4=TRUE(),P47=TRUE()) -> #REF! | Q3: =AND(Q4=TRUE(),Q47=TRUE()) -> #REF! | R3: =AND(R4=TRUE(),R47=TRUE()) -> #REF!
A4: VEHICLE_ACTIVATION | C4: Vehicle activation | K4: VRAI / FAUX | M4: VRAI | N4: VRAI | O4: VRAI | P4: VRAI | Q4: VRAI | R4: VRAI
C5: Vehicle ref | K5: ref | M5: =L5+1 -> 1 | N5: =M5+1 -> 2 | O5: =N5+1 -> 3 | P5: =O5+1 -> 4 | Q5: =P5+1 -> 5 | R5: =Q5+1 -> 6
A6: VEHICLE_TYPE | C6: Vehicle type | K6: list | M6: Holdco | N6: Holdco | O6: Holdco | P6: SPV | Q6: SPV | R6: SPV
B8: 1 | C8: VEHICLE TYPE AND DETENTION
C10: Vehicle name
C11: {=TRANSPOSE(Name_Vehicle_Row)} -> #REF! | S11: u
C12: #REF!
C13: #REF!
C14: #REF!
C15: #REF!
C16: SPV_3
C17: =#N/A -> #N/A
C18: =#N/A -> #N/A
C19: =#N/A -> #N/A
C20: =#N/A -> #N/A
C21: =#N/A -> #N/A
C22: =#N/A -> #N/A
C23: =#N/A -> #N/A
C24: =#N/A -> #N/A
C25: =#N/A -> #N/A
C26: =#N/A -> #N/A
C27: =#N/A -> #N/A
C28: =#N/A -> #N/A
... C40: =#N/A -> #N/A
A41: VEHICLE_PARENT_NAME | C41: Holding vehicle name | K41: list | M41: TopCo | N41: TopCo | O41: TopCo | P41: Holdco_1 | Q41: Holdco_2 | R41: Holdco_1
C42: Holding vehicle type | K42: VRAI/FAUX | M42: =TRUE() -> TRUE | N42: =TRUE() -> TRUE | P42: =FALSE() -> FALSE | Q42: =FALSE() -> FALSE | R42: =FALSE() -> FALSE
C43: Vehicle held by (ref) | K43: ref_Vehicle | M43: =IF(M3,MATCH(M41,$M$2:$R$2,0),0) -> #REF! | N43: =IF(N3,MATCH(N41,$M$2:$R$2,0),0) -> #REF! | P43: =IF(P3,MATCH(P41,$M$2:$R$2,0),0) -> #REF! | Q43: =IF(Q3,MATCH(Q41,$M$2:$R$2,0),0) -> #REF! | R43: =IF(R3,MATCH(R41,$M$2:$R$2,0),0) -> #REF!
C44: Ref Perimeter (senior facility) | K44: ref_Perimeter | M44: =IF(M$51,M5,M43) -> #REF! | N44: =IF(N$51,N5,N43) -> #REF! | P44: =IF(P$51,P5,P43) -> 4 | Q44: =IF(Q$51,Q5,Q43) -> 5 | R44: =IF(R$51,R5,R43) -> 6
C45: Detention by holdco | K45: % | M45: 1 | N45: 1 | O45: 1 | P45: 1 | Q45: 1 | R45: 1
C46: Check vehicle detention | H46: check | I46: =COUNTIF($M$46:$R$46,FALSE())=0 -> 1 | K46: VRAI/FAUX | M46: =IF(OR(M6="",M3<>TRUE()),TRUE(),AND(M45>0,M45<=1)) -> #REF! | N46: =IF(OR(N6="",N3<>TRUE()),TRUE(),AND(N45>0,N45<=1)) -> #REF! | O46: =IF(OR(O6="",O3<>TRUE()),TRUE(),AND(O45>0,O45<=1)) -> 1 | P46: =IF(OR(P6="",P3<>TRUE()),TRUE(),AND(P45>0,P45<=1)) -> #REF! | Q46: =IF(OR(Q6="",Q3<>TRUE()),TRUE(),AND(Q45>0,Q45<=1)) -> #REF! | R46: =IF(OR(R6="",R3<>TRUE()),TRUE(),AND(R45>0,R45<=1)) -> #REF!
C47: Check vehicle duplication | H47: check | I47: =COUNTIF($M$47:$R$47,FALSE())=0 -> 1 | K47: VRAI/FAUX | M47: {=IF(M$4=FALSE(),TRUE(),IF(IFERROR(INDIRECT("'"&M$2&"'!A1"),FALSE())=0,TRUE()))} -> #REF! | N47: {=IF(N$4=FALSE(),TRUE(),IF(IFERROR(INDIRECT("'"&N$2&"'!A1"),FALSE())=0,TRUE()))} -> #REF! | O47: =IF(OR(O7="",O4<>TRUE()),TRUE(),AND(O46>0,O46<=1)) -> 1 | P47: {=IF(P$4=FALSE(),TRUE(),IF(IFERROR(INDIRECT("'"&P$2&"'!A1"),FALSE())=0,TRUE()))} -> #REF! | Q47: {=IF(Q$4=FALSE(),TRUE(),IF(IFERROR(INDIRECT("'"&Q$2&"'!A1"),FALSE())=0,TRUE()))} -> #REF! | R47: {=IF(R$4=FALSE(),TRUE(),IF(IFERROR(INDIRECT("'"&R$2&"'!A1"),FALSE())=0,TRUE()))} -> #REF!
B49: 2 | C49: DEBT FACILITIES
C51: Sernior facility activation | K51: VRAI/FAUX | N51: =FALSE() -> FALSE | P51: =TRUE() -> TRUE | Q51: =TRUE() -> TRUE | R51: =TRUE() -> TRUE
C53: SENIOR DEBT
C54: Timing
C55: Financial close | K55: date | N55: 45930 | P55: 45930 | Q55: 45930 | R55: 45930
I56: Phase
C57: ="Last COD phase "&I57 -> Last COD phase 1 | H57: ref | I57: {=ass_Model!$M$114:$M$121} -> 1 | K57: date | N57: =_xlfn.MAXIFS(Construction_End,Vehicle_Asset,N$2) -> #VALUE! | P57: =_xlfn.MAXIFS(Construction_End,Vehicle_Asset,P$2,Asset_Activation,TRUE()) -> #VALUE! | Q57: =_xlfn.MAXIFS(Construction_End,Vehicle_Asset,Q$2,Asset_Activation,TRUE()) -> #VALUE! | R57: =_xlfn.MAXIFS(Construction_End,Vehicle_Asset,R$2) -> #VALUE!
C58: ="Last COD phase "&I58 -> Last COD phase 2 | H58: ref | I58: 2 | K58: date
C59: ="Last COD phase "&I59 -> Last COD phase 3 | H59: ref | I59: 3 | K59: date
C60: ="Last COD phase "&I60 -> Last COD phase 4 | H60: ref | I60: 4 | K60: date
C61: ="Last COD phase "&I61 -> Last COD phase 5 | H61: ref | I61: 5 | K61: date
C62: ="Last COD phase "&I62 -> Last COD phase 6 | H62: ref | I62: 6 | K62: date
C63: ="Last COD phase "&I63 -> Last COD phase 7 | H63: ref | I63: 7 | K63: date
C64: ="Last COD phase "&I64 -> Last COD phase 8 | H64: ref | I64: 8 | K64: date
C66: ="Phase "&I57&" Activation" -> Phase 1 Activation | K66: VRAI/FAUX | N66: =TRUE() -> TRUE | P66: =TRUE() -> TRUE | Q66: =TRUE() -> TRUE | R66: =TRUE() -> TRUE
C67: ="Phase "&I58&" Activation" -> Phase 2 Activation | K67: VRAI/FAUX
C68: ="Phase "&I59&" Activation" -> Phase 3 Activation | K68: VRAI/FAUX
C69: ="Phase "&I60&" Activation" -> Phase 4 Activation | K69: VRAI/FAUX
C70: ="Phase "&I61&" Activation" -> Phase 5 Activation | K70: VRAI/FAUX
C71: ="Phase "&I62&" Activation" -> Phase 6 Activation | K71: VRAI/FAUX
C72: ="Phase "&I63&" Activation" -> Phase 7 Activation | K72: VRAI/FAUX
C73: ="Phase "&I64&" Activation" -> Phase 8 Activation | K73: VRAI/FAUX
C75: Last phase activation | K75: ref phase | M75: {=IF(AND(SUM(M57:M64)>0,M51=TRUE(),M3=TRUE()),MATCH(MAX(M57:M64*M66:M73),M57:M64*M66:M73,),0)} -> #REF! | N75: {=IF(AND(SUM(N57:N64)>0,N51=TRUE(),N3=TRUE()),MATCH(MAX(N57:N64*N66:N73),N57:N64*N66:N73,),0)} -> #VALUE! | P75: {=IF(AND(SUM(P57:P64)>0,P51=TRUE(),P3=TRUE()),MATCH(MAX(P57:P64*P66:P73),P57:P64*P66:P73,),0)} -> #VALUE! | Q75: {=IF(AND(SUM(Q57:Q64)>0,Q51=TRUE(),Q3=TRUE()),MATCH(MAX(Q57:Q64*Q66:Q73),Q57:Q64*Q66:Q73,),0)} -> #VALUE! | R75: {=IF(AND(SUM(R57:R64)>0,R51=TRUE(),R3=TRUE()),MATCH(MAX(R57:R64*R66:R73),R57:R64*R66:R73,),0)} -> #VALUE!
C77: Grace period adjusted on Interest payment date | K77: VRAI/FAUX | N77: =FALSE() -> FALSE | P77: =FALSE() -> FALSE | Q77: =FALSE() -> FALSE | R77: =FALSE() -> FALSE
C79: Drawdown period start | K79: date | M79: =IF(AND(M51=TRUE(),M3=TRUE()),M55,) -> #REF! | N79: =IF(AND(N51=TRUE(),N3=TRUE()),N55,) -> #REF! | P79: =IF(AND(P51=TRUE(),P3=TRUE()),P55,) -> #REF! | Q79: =IF(AND(Q51=TRUE(),Q3=TRUE()),Q55,) -> #REF! | R79: =IF(AND(R51=TRUE(),R3=TRUE()),R55,) -> #REF!
C80: Drawdown period end | K80: date | M80: =IF(AND(M51=TRUE(),M3=TRUE()),IF(Phase=9,MAX(M57:M64*M66:M73,M55),MAX(INDEX(M57:M64*M66:M73,Phase,),M55)),) -> #REF! | N80: =IF(AND(N51=TRUE(),N3=TRUE()),IF(Phase=9,MAX(N57:N64*N66:N73,N55),MAX(INDEX(N57:N64*N66:N73,Phase,),N55)),) -> #REF! | P80: {=IF(AND(P51=TRUE(),P3=TRUE()),IF(Phase=9,MAX(P57:P64*P66:P73,P55),MAX(INDEX(P57:P64*P66:P73,Phase,),P55)),)} -> #REF! | Q80: {=IF(AND(Q51=TRUE(),Q3=TRUE()),IF(Phase=9,MAX(Q57:Q64*Q66:Q73,Q55),MAX(INDEX(Q57:Q64*Q66:Q73,Phase,),Q55)),)} -> #REF! | R80: {=IF(AND(R51=TRUE(),R3=TRUE()),IF(Phase=9,MAX(R57:R64*R66:R73,R55),MAX(INDEX(R57:R64*R66:R73,Phase,),R55)),)} -> #REF!
C82: ="Consolidation date of Phase 1 if "&C83 -> Consolidation date of Phase 1 if Consolidation before Last COD Activation | K82: date
C83: Consolidation before Last COD Activation | K83: VRAI/FAUX
C84: Consolidation date | K84: date | M84: =IF(AND(M51=TRUE(),M3=TRUE()),IF($N$83,M82,EDATE(IF(Phase=9,_xlfn.MINIFS(M57:M64,M66:M73,TRUE()),M80)+1,M233*(M234=FALSE()))),0) -> #REF! | N84: =IF(AND(N51=TRUE(),N3=TRUE()),IF($N$83,N82,EDATE(IF(Phase=9,_xlfn.MINIFS(N57:N64,N66:N73,TRUE()),N80)+1,N233*(N234=FALSE()))),0) -> #REF! | P84: =IF(AND(P51=TRUE(),P3=TRUE()),IF($N$83,P82,EDATE(IF(Phase=9,_xlfn.MINIFS(P57:P64,P66:P73,TRUE()),P80)+1,P233*(P234=FALSE()))),0) -> #REF! | Q84: =IF(AND(Q51=TRUE(),Q3=TRUE()),IF($N$83,Q82,EDATE(IF(Phase=9,_xlfn.MINIFS(Q57:Q64,Q66:Q73,TRUE()),Q80)+1,Q233*(Q234=FALSE()))),0) -> #REF! | R84: =IF(AND(R51=TRUE(),R3=TRUE()),IF($N$83,R82,EDATE(IF(Phase=9,_xlfn.MINIFS(R57:R64,R66:R73,TRUE()),R80)+1,R233*(R234=FALSE()))),0) -> #REF!
C85: Grace period | K85: months | N85: 9 | P85: 9 | Q85: 9 | R85: 9
C86: Repayment start | K86: date | M86: =IF(AND(M$51=TRUE(),M$3=TRUE()),IF(OR(Phase=1,Phase=9),EDATE(M$84,M$85),IF(M$77,EDATE(M79,ROUNDDOWN((M$80-M$79)/(30.5*3)+M$85/3,0)*3),EDATE(M$84,M$85)))) -> #REF! | N86: =IF(AND(N$51=TRUE(),N$3=TRUE()),IF(OR(Phase=1,Phase=9),EDATE(N$84,N$85),IF(N$77,EDATE(N79,ROUNDDOWN((N$80-N$79)/(30.5*3)+N$85/3,0)*3),EDATE(N$84,N$85)))) -> #REF! | P86: =IF(AND(P$51=TRUE(),P$3=TRUE()),IF(OR(Phase=1,Phase=9),EDATE(P$84,P$85),IF(P$77,EDATE(P79,ROUNDDOWN((P$80-P$79)/(30.5*3)+P$85/3,0)*3),EDATE(P$84,P$85)))) -> #REF! | Q86: =IF(AND(Q$51=TRUE(),Q$3=TRUE()),IF(OR(Phase=1,Phase=9),EDATE(Q$84,Q$85),IF(Q$77,EDATE(Q79,ROUNDDOWN((Q$80-Q$79)/(30.5*3)+Q$85/3,0)*3),EDATE(Q$84,Q$85)))) -> #REF! | R86: =IF(AND(R$51=TRUE(),R$3=TRUE()),IF(OR(Phase=1,Phase=9),EDATE(R$84,R$85),IF(R$77,EDATE(R79,ROUNDDOWN((R$80-R$79)/(30.5*3)+R$85/3,0)*3),EDATE(R$84,R$85)))) -> #REF!
C87: Duration | K87: years | M87: =YEARFRAC(M84,M88,1) -> #VALUE! | N87: =YEARFRAC(N84,N88,1) -> #VALUE! | P87: =YEARFRAC(P84,P88,1) -> #VALUE! | Q87: =YEARFRAC(Q84,Q88,1) -> #VALUE! | R87: =YEARFRAC(R84,R88,1) -> #VALUE!
C88: Repayment end | K88: date | M88: =_xlfn.MAXIFS(#REF!,Perimeter_Asset,M$5) -> #VALUE! | N88: =_xlfn.MAXIFS(#REF!,Perimeter_Asset,N$5) -> #VALUE! | P88: =_xlfn.MAXIFS(#REF!,Perimeter_Asset,P$5) -> #VALUE! | Q88: =_xlfn.MAXIFS(#REF!,Perimeter_Asset,Q$5) -> #VALUE! | R88: =_xlfn.MAXIFS(#REF!,Perimeter_Asset,R$5) -> #VALUE!
C90: Repayment periodicity | K90: months | N90: 3 | P90: 3 | Q90: 3 | R90: 3
C92: Interest period per phase post consolidation
C93: ="Phase "&I93 -> Phase 1 | G93: Phase | H93: ref | I93: 1
C94: Start | K94: date | M94: {=IF($N$83,M82,INDEX(M$57:M$64,$I93,)+1)} -> 1 | N94: {=IF($N$83,N82,INDEX(N$57:N$64,$I93,)+1)} -> #VALUE! | P94: {=IF($N$83,P82,INDEX(P$57:P$64,$I93,)+1)} -> #VALUE! | Q94: {=IF($N$83,Q82,INDEX(Q$57:Q$64,$I93,)+1)} -> #VALUE! | R94: {=IF($N$83,R82,INDEX(R$57:R$64,$I93,)+1)} -> #VALUE!
C95: End | K95: date | M95: =_xlfn.MAXIFS(#REF!,#REF!,$I93,#REF!,M$5) -> #VALUE! | N95: =_xlfn.MAXIFS(#REF!,#REF!,$I93,#REF!,N$5) -> #VALUE! | P95: =_xlfn.MAXIFS(#REF!,#REF!,$I93,#REF!,P$5) -> #VALUE! | Q95: =_xlfn.MAXIFS(#REF!,#REF!,$I93,#REF!,Q$5) -> #VALUE! | R95: =_xlfn.MAXIFS(#REF!,#REF!,$I93,#REF!,R$5) -> #VALUE!
C97: ="Phase "&I97 -> Phase 2 | G97: Phase | H97: ref | I97: =I93+1 -> 2
C98: Start | K98: date | M98: {=INDEX(M$57:M$64,$I97,)+1} -> 1 | N98: {=INDEX(N$57:N$64,$I97,)+1} -> 1 | P98: {=INDEX(P$57:P$64,$I97,)+1} -> 1 | Q98: {=INDEX(Q$57:Q$64,$I97,)+1} -> 1 | R98: {=INDEX(R$57:R$64,$I97,)+1} -> 1
C99: End | K99: date | M99: =_xlfn.MAXIFS(#REF!,#REF!,$I97,#REF!,M$5) -> #VALUE! | N99: =_xlfn.MAXIFS(#REF!,#REF!,$I97,#REF!,N$5) -> #VALUE! | P99: =_xlfn.MAXIFS(#REF!,#REF!,$I97,#REF!,P$5) -> #VALUE! | Q99: =_xlfn.MAXIFS(#REF!,#REF!,$I97,#REF!,Q$5) -> #VALUE! | R99: =_xlfn.MAXIFS(#REF!,#REF!,$I97,#REF!,R$5) -> #VALUE!
C101: ="Phase "&I101 -> Phase 3 | G101: Phase | H101: ref | I101: =I97+1 -> 3
C102: Start | K102: date | M102: {=INDEX(M$57:M$64,$I101,)+1} -> 1 | N102: {=INDEX(N$57:N$64,$I101,)+1} -> 1 | P102: {=INDEX(P$57:P$64,$I101,)+1} -> 1 | Q102: {=INDEX(Q$57:Q$64,$I101,)+1} -> 1 | R102: {=INDEX(R$57:R$64,$I101,)+1} -> 1
C103: End | K103: date | M103: =_xlfn.MAXIFS(#REF!,#REF!,$I101,#REF!,M$5) -> #VALUE! | N103: =_xlfn.MAXIFS(#REF!,#REF!,$I101,#REF!,N$5) -> #VALUE! | P103: =_xlfn.MAXIFS(#REF!,#REF!,$I101,#REF!,P$5) -> #VALUE! | Q103: =_xlfn.MAXIFS(#REF!,#REF!,$I101,#REF!,Q$5) -> #VALUE! | R103: =_xlfn.MAXIFS(#REF!,#REF!,$I101,#REF!,R$5) -> #VALUE!
C105: ="Phase "&I105 -> Phase 4 | G105: Phase | H105: ref | I105: =I101+1 -> 4
C106: Start | K106: date | M106: {=INDEX(M$57:M$64,$I105,)+1} -> 1 | N106: {=INDEX(N$57:N$64,$I105,)+1} -> 1 | P106: {=INDEX(P$57:P$64,$I105,)+1} -> 1 | Q106: {=INDEX(Q$57:Q$64,$I105,)+1} -> 1 | R106: {=INDEX(R$57:R$64,$I105,)+1} -> 1
C107: End | K107: date | M107: =_xlfn.MAXIFS(#REF!,#REF!,$I105,#REF!,M$5) -> #VALUE! | N107: =_xlfn.MAXIFS(#REF!,#REF!,$I105,#REF!,N$5) -> #VALUE! | P107: =_xlfn.MAXIFS(#REF!,#REF!,$I105,#REF!,P$5) -> #VALUE! | Q107: =_xlfn.MAXIFS(#REF!,#REF!,$I105,#REF!,Q$5) -> #VALUE! | R107: =_xlfn.MAXIFS(#REF!,#REF!,$I105,#REF!,R$5) -> #VALUE!
C109: ="Phase "&I109 -> Phase 5 | G109: Phase | H109: ref | I109: =I105+1 -> 5
C110: Start | K110: date | M110: {=INDEX(M$57:M$64,$I109,)+1} -> 1 | N110: {=INDEX(N$57:N$64,$I109,)+1} -> 1 | P110: {=INDEX(P$57:P$64,$I109,)+1} -> 1 | Q110: {=INDEX(Q$57:Q$64,$I109,)+1} -> 1 | R110: {=INDEX(R$57:R$64,$I109,)+1} -> 1
C111: End | K111: date | M111: =_xlfn.MAXIFS(#REF!,#REF!,$I109,#REF!,M$5) -> #VALUE! | N111: =_xlfn.MAXIFS(#REF!,#REF!,$I109,#REF!,N$5) -> #VALUE! | P111: =_xlfn.MAXIFS(#REF!,#REF!,$I109,#REF!,P$5) -> #VALUE! | Q111: =_xlfn.MAXIFS(#REF!,#REF!,$I109,#REF!,Q$5) -> #VALUE! | R111: =_xlfn.MAXIFS(#REF!,#REF!,$I109,#REF!,R$5) -> #VALUE!
C113: ="Phase "&I113 -> Phase 6 | G113: Phase | H113: ref | I113: =I109+1 -> 6
C114: Start | K114: date | M114: {=INDEX(M$57:M$64,$I113,)+1} -> 1 | N114: {=INDEX(N$57:N$64,$I113,)+1} -> 1 | P114: {=INDEX(P$57:P$64,$I113,)+1} -> 1 | Q114: {=INDEX(Q$57:Q$64,$I113,)+1} -> 1 | R114: {=INDEX(R$57:R$64,$I113,)+1} -> 1
C115: End | K115: date | M115: =_xlfn.MAXIFS(#REF!,#REF!,$I113,#REF!,M$5) -> #VALUE! | N115: =_xlfn.MAXIFS(#REF!,#REF!,$I113,#REF!,N$5) -> #VALUE! | P115: =_xlfn.MAXIFS(#REF!,#REF!,$I113,#REF!,P$5) -> #VALUE! | Q115: =_xlfn.MAXIFS(#REF!,#REF!,$I113,#REF!,Q$5) -> #VALUE! | R115: =_xlfn.MAXIFS(#REF!,#REF!,$I113,#REF!,R$5) -> #VALUE!
C117: ="Phase "&I117 -> Phase 7 | G117: Phase | H117: ref | I117: =I113+1 -> 7
C118: Start | K118: date | M118: {=INDEX(M$57:M$64,$I117,)+1} -> 1 | N118: {=INDEX(N$57:N$64,$I117,)+1} -> 1 | P118: {=INDEX(P$57:P$64,$I117,)+1} -> 1 | Q118: {=INDEX(Q$57:Q$64,$I117,)+1} -> 1 | R118: {=INDEX(R$57:R$64,$I117,)+1} -> 1
C119: End | K119: date | M119: =_xlfn.MAXIFS(#REF!,#REF!,$I117,#REF!,M$5) -> #VALUE! | N119: =_xlfn.MAXIFS(#REF!,#REF!,$I117,#REF!,N$5) -> #VALUE! | P119: =_xlfn.MAXIFS(#REF!,#REF!,$I117,#REF!,P$5) -> #VALUE! | Q119: =_xlfn.MAXIFS(#REF!,#REF!,$I117,#REF!,Q$5) -> #VALUE! | R119: =_xlfn.MAXIFS(#REF!,#REF!,$I117,#REF!,R$5) -> #VALUE!
C121: ="Phase "&I121 -> Phase 8 | G121: Phase | H121: ref | I121: =I117+1 -> 8
C122: Start | K122: date | M122: {=INDEX(M$57:M$64,$I121,)+1} -> 1 | N122: {=INDEX(N$57:N$64,$I121,)+1} -> 1 | P122: {=INDEX(P$57:P$64,$I121,)+1} -> 1 | Q122: {=INDEX(Q$57:Q$64,$I121,)+1} -> 1 | R122: {=INDEX(R$57:R$64,$I121,)+1} -> 1
C123: End | K123: date | M123: =_xlfn.MAXIFS(#REF!,#REF!,$I121,#REF!,M$5) -> #VALUE! | N123: =_xlfn.MAXIFS(#REF!,#REF!,$I121,#REF!,N$5) -> #VALUE! | P123: =_xlfn.MAXIFS(#REF!,#REF!,$I121,#REF!,P$5) -> #VALUE! | Q123: =_xlfn.MAXIFS(#REF!,#REF!,$I121,#REF!,Q$5) -> #VALUE! | R123: =_xlfn.MAXIFS(#REF!,#REF!,$I121,#REF!,R$5) -> #VALUE!
C125: Interest rate - Lenders
C126: ="Credit Margin - phase "&I126 -> Credit Margin - phase 1 | H126: ref | I126: 1 | K126: % | N126: =1.14%*40%+1.19%*60% -> 0.0117 | P126: =1.14%*40%+1.19%*60% -> 0.0117 | Q126: =1.14%*40%+1.19%*60% -> 0.0117 | R126: =1.14%*40%+1.19%*60% -> 0.0117
C127: ="Credit Margin - phase "&I127 -> Credit Margin - phase 2 | H127: ref | I127: =I126+1 -> 2 | K127: %
C128: ="Credit Margin - phase "&I128 -> Credit Margin - phase 3 | H128: ref | I128: =I127+1 -> 3 | K128: %
C129: ="Credit Margin - phase "&I129 -> Credit Margin - phase 4 | H129: ref | I129: =I128+1 -> 4 | K129: %
C130: ="Credit Margin - phase "&I130 -> Credit Margin - phase 5 | H130: ref | I130: =I129+1 -> 5 | K130: %
C131: ="Credit Margin - phase "&I131 -> Credit Margin - phase 6 | H131: ref | I131: =I130+1 -> 6 | K131: %
C132: ="Credit Margin - phase "&I132 -> Credit Margin - phase 7 | H132: ref | I132: =I131+1 -> 7 | K132: %
...

Sheet ass_Market
B6: 1 | C6: INFLATION
C8: FORECASTS
A9: MARKET_IPC_SCENARIO | C9: Inflation scenario | E9: Index | F9: IPC | G9: =G$10*10^2&"% IPC" -> 20% IPC | H9: =H$10*10^2&"% IPC" -> 30% IPC | I9: =I$10*10^2&"% IPC" -> 40% IPC | M9: Index | N9: {=F9:L9} -> IPC | O9: 20% IPC | P9: 30% IPC | Q9: 40% IPC | R9: 0 | S9: 0 | T9: 0 | V9: Index | W9: =N9 -> IPC | X9: =O9 -> 20% IPC | Y9: =P9 -> 30% IPC | Z9: =Q9 -> 40% IPC | AA9: =R9 -> 0 | AB9: =S9 -> 0 | AC9: =T9 -> 0
A10: MARKET_IPC_PERCENTAGES | G10: 0.2 | H10: 0.3 | I10: 0.4
B11: ref | C11: Year
A12: MARKET_IPC_YEAR_START | B12: 1 | C12: =YEAR(Model_Start_Date) -> 2025 | E12: % per year | F12: 0.02 | G12: =G$10*$F12 -> 0.004 | H12: =H$10*$F12 -> 0.006 | I12: =I$10*$F12 -> 0.008 | M12: % per year | N12: {=IF(sensi=1,F$12:F$63+Dashboard!$M$139,F$12:F$63)} -> 0.02 | O12: {=IF(sensi=1,G$12:G$63+Dashboard!$M$139*$G$10,G$12:G$63)} -> 0.004 | P12: {=IF(sensi=1,H$12:H$63+Dashboard!$M$139,H$12:H$63)} -> 0.006 | Q12: {=IF(sensi=1,I$12:I$63+Dashboard!$M$139,I$12:I$63)} -> 0.008 | R12: {=IF(sensi=1,J$12:J$63+Dashboard!$M$139,J$12:J$63)} -> 0 | S12: {=IF(sensi=1,K$12:K$63+Dashboard!$M$139,K$12:K$63)} -> 0 | T12: {=IF(sensi=1,L$12:L$63+Dashboard!$M$139,L$12:L$63)} -> 0 | V12: % per year | W12: =IF($C12=YEAR(Model_Start_Date),1,W11*(1+N12)) -> 1 | X12: =IF($C12=YEAR(Model_Start_Date),1,X11*(1+O12)) -> 1 | Y12: =IF($C12=YEAR(Model_Start_Date),1,Y11*(1+P12)) -> 1 | Z12: =IF($C12=YEAR(Model_Start_Date),1,Z11*(1+Q12)) -> 1 | AA12: =IF($C12=YEAR(Model_Start_Date),1,AA11*(1+R12)) -> 1 | AB12: =IF($C12=YEAR(Model_Start_Date),1,AB11*(1+S12)) -> 1 | AC12: =IF($C12=YEAR(Model_Start_Date),1,AC11*(1+T12)) -> 1
B13: =B12+1 -> 2 | C13: =C12+1 -> 2026 | E13: % per year | F13: 0.02 | G13: =G$10*$F13 -> 0.004 | H13: =H$10*$F13 -> 0.006 | I13: =I$10*$F13 -> 0.008 | M13: % per year | N13: 0.02 | O13: 0.004 | P13: 0.006 | Q13: 0.008 | R13: 0 | S13: 0 | T13: 0 | V13: % per year | W13: =IF($C13=YEAR(Model_Start_Date),1,W12*(1+N13)) -> 1.02 | X13: =IF($C13=YEAR(Model_Start_Date),1,X12*(1+O13)) -> 1.004 | Y13: =IF($C13=YEAR(Model_Start_Date),1,Y12*(1+P13)) -> 1.006 | Z13: =IF($C13=YEAR(Model_Start_Date),1,Z12*(1+Q13)) -> 1.008 | AA13: =IF($C13=YEAR(Model_Start_Date),1,AA12*(1+R13)) -> 1 | AB13: =IF($C13=YEAR(Model_Start_Date),1,AB12*(1+S13)) -> 1 | AC13: =IF($C13=YEAR(Model_Start_Date),1,AC12*(1+T13)) -> 1
B14: =B13+1 -> 3 | C14: =C13+1 -> 2027 | E14: % per year | F14: 0.02 | G14: =G$10*$F14 -> 0.004 | H14: =H$10*$F14 -> 0.006 | I14: =I$10*$F14 -> 0.008 | M14: % per year | N14: 0.02 | O14: 0.004 | P14: 0.006 | Q14: 0.008 | R14: 0 | S14: 0 | T14: 0 | V14: % per year | W14: =IF($C14=YEAR(Model_Start_Date),1,W13*(1+N14)) -> 1.0404 | X14: =IF($C14=YEAR(Model_Start_Date),1,X13*(1+O14)) -> 1.008016 | Y14: =IF($C14=YEAR(Model_Start_Date),1,Y13*(1+P14)) -> 1.012036 | Z14: =IF($C14=YEAR(Model_Start_Date),1,Z13*(1+Q14)) -> 1.016064 | AA14: =IF($C14=YEAR(Model_Start_Date),1,AA13*(1+R14)) -> 1 | AB14: =IF($C14=YEAR(Model_Start_Date),1,AB13*(1+S14)) -> 1 | AC14: =IF($C14=YEAR(Model_Start_Date),1,AC13*(1+T14)) -> 1
B15: =B14+1 -> 4 | C15: =C14+1 -> 2028 | E15: % per year | F15: 0.02 | G15: =G$10*$F15 -> 0.004 | H15: =H$10*$F15 -> 0.006 | I15: =I$10*$F15 -> 0.008 | M15: % per year | N15: 0.02 | O15: 0.004 | P15: 0.006 | Q15: 0.008 | R15: 0 | S15: 0 | T15: 0 | V15: % per year | W15: =IF($C15=YEAR(Model_Start_Date),1,W14*(1+N15)) -> 1.061208 | X15: =IF($C15=YEAR(Model_Start_Date),1,X14*(1+O15)) -> 1.0120481 | Y15: =IF($C15=YEAR(Model_Start_Date),1,Y14*(1+P15)) -> 1.0181082 | Z15: =IF($C15=YEAR(Model_Start_Date),1,Z14*(1+Q15)) -> 1.0241925 | AA15: =IF($C15=YEAR(Model_Start_Date),1,AA14*(1+R15)) -> 1 | AB15: =IF($C15=YEAR(Model_Start_Date),1,AB14*(1+S15)) -> 1 | AC15: =IF($C15=YEAR(Model_Start_Date),1,AC14*(1+T15)) -> 1
B16: =B15+1 -> 5 | C16: =C15+1 -> 2029 | E16: % per year | F16: 0.02 | G16: =G$10*$F16 -> 0.004 | H16: =H$10*$F16 -> 0.006 | I16: =I$10*$F16 -> 0.008 | M16: % per year | N16: 0.02 | O16: 0.004 | P16: 0.006 | Q16: 0.008 | R16: 0 | S16: 0 | T16: 0 | V16: % per year | W16: =IF($C16=YEAR(Model_Start_Date),1,W15*(1+N16)) -> 1.0824322 | X16: =IF($C16=YEAR(Model_Start_Date),1,X15*(1+O16)) -> 1.0160963 | Y16: =IF($C16=YEAR(Model_Start_Date),1,Y15*(1+P16)) -> 1.0242169 | Z16: =IF($C16=YEAR(Model_Start_Date),1,Z15*(1+Q16)) -> 1.0323861 | AA16: =IF($C16=YEAR(Model_Start_Date),1,AA15*(1+R16)) -> 1 | AB16: =IF($C16=YEAR(Model_Start_Date),1,AB15*(1+S16)) -> 1 | AC16: =IF($C16=YEAR(Model_Start_Date),1,AC15*(1+T16)) -> 1
B17: =B16+1 -> 6 | C17: =C16+1 -> 2030 | E17: % per year | F17: 0.02 | G17: =G$10*$F17 -> 0.004 | H17: =H$10*$F17 -> 0.006 | I17: =I$10*$F17 -> 0.008 | M17: % per year | N17: 0.02 | O17: 0.004 | P17: 0.006 | Q17: 0.008 | R17: 0 | S17: 0 | T17: 0 | V17: % per year | W17: =IF($C17=YEAR(Model_Start_Date),1,W16*(1+N17)) -> 1.1040808 | X17: =IF($C17=YEAR(Model_Start_Date),1,X16*(1+O17)) -> 1.0201606 | Y17: =IF($C17=YEAR(Model_Start_Date),1,Y16*(1+P17)) -> 1.0303622 | Z17: =IF($C17=YEAR(Model_Start_Date),1,Z16*(1+Q17)) -> 1.0406451 | AA17: =IF($C17=YEAR(Model_Start_Date),1,AA16*(1+R17)) -> 1 | AB17: =IF($C17=YEAR(Model_Start_Date),1,AB16*(1+S17)) -> 1 | AC17: =IF($C17=YEAR(Model_Start_Date),1,AC16*(1+T17)) -> 1
B18: =B17+1 -> 7 | C18: =C17+1 -> 2031 | E18: % per year | F18: 0.02 | G18: =G$10*$F18 -> 0.004 | H18: =H$10*$F18 -> 0.006 | I18: =I$10*$F18 -> 0.008 | M18: % per year | N18: 0.02 | O18: 0.004 | P18: 0.006 | Q18: 0.008 | R18: 0 | S18: 0 | T18: 0 | V18: % per year | W18: =IF($C18=YEAR(Model_Start_Date),1,W17*(1+N18)) -> 1.1261624 | X18: =IF($C18=YEAR(Model_Start_Date),1,X17*(1+O18)) -> 1.0242413 | Y18: =IF($C18=YEAR(Model_Start_Date),1,Y17*(1+P18)) -> 1.0365443 | Z18: =IF($C18=YEAR(Model_Start_Date),1,Z17*(1+Q18)) -> 1.0489703 | AA18: =IF($C18=YEAR(Model_Start_Date),1,AA17*(1+R18)) -> 1 | AB18: =IF($C18=YEAR(Model_Start_Date),1,AB17*(1+S18)) -> 1 | AC18: =IF($C18=YEAR(Model_Start_Date),1,AC17*(1+T18)) -> 1
B19: =B18+1 -> 8 | C19: =C18+1 -> 2032 | E19: % per year | F19: 0.02 | G19: =G$10*$F19 -> 0.004 | H19: =H$10*$F19 -> 0.006 | I19: =I$10*$F19 -> 0.008 | M19: % per year | N19: 0.02 | O19: 0.004 | P19: 0.006 | Q19: 0.008 | R19: 0 | S19: 0 | T19: 0 | V19: % per year | W19: =IF($C19=YEAR(Model_Start_Date),1,W18*(1+N19)) -> 1.1486857 | X19: =IF($C19=YEAR(Model_Start_Date),1,X18*(1+O19)) -> 1.0283382 | Y19: =IF($C19=YEAR(Model_Start_Date),1,Y18*(1+P19)) -> 1.0427636 | Z19: =IF($C19=YEAR(Model_Start_Date),1,Z18*(1+Q19)) -> 1.0573621 | AA19: =IF($C19=YEAR(Model_Start_Date),1,AA18*(1+R19)) -> 1 | AB19: =IF($C19=YEAR(Model_Start_Date),1,AB18*(1+S19)) -> 1 | AC19: =IF($C19=YEAR(Model_Start_Date),1,AC18*(1+T19)) -> 1
B20: =B19+1 -> 9 | C20: =C19+1 -> 2033 | E20: % per year | F20: 0.02 | G20: =G$10*$F20 -> 0.004 | H20: =H$10*$F20 -> 0.006 | I20: =I$10*$F20 -> 0.008 | M20: % per year | N20: 0.02 | O20: 0.004 | P20: 0.006 | Q20: 0.008 | R20: 0 | S20: 0 | T20: 0 | V20: % per year | W20: =IF($C20=YEAR(Model_Start_Date),1,W19*(1+N20)) -> 1.1716594 | X20: =IF($C20=YEAR(Model_Start_Date),1,X19*(1+O20)) -> 1.0324516 | Y20: =IF($C20=YEAR(Model_Start_Date),1,Y19*(1+P20)) -> 1.0490202 | Z20: =IF($C20=YEAR(Model_Start_Date),1,Z19*(1+Q20)) -> 1.065821 | AA20: =IF($C20=YEAR(Model_Start_Date),1,AA19*(1+R20)) -> 1 | AB20: =IF($C20=YEAR(Model_Start_Date),1,AB19*(1+S20)) -> 1 | AC20: =IF($C20=YEAR(Model_Start_Date),1,AC19*(1+T20)) -> 1
B21: =B20+1 -> 10 | C21: =C20+1 -> 2034 | E21: % per year | F21: 0.02 | G21: =G$10*$F21 -> 0.004 | H21: =H$10*$F21 -> 0.006 | I21: =I$10*$F21 -> 0.008 | M21: % per year | N21: 0.02 | O21: 0.004 | P21: 0.006 | Q21: 0.008 | R21: 0 | S21: 0 | T21: 0 | V21: % per year | W21: =IF($C21=YEAR(Model_Start_Date),1,W20*(1+N21)) -> 1.1950926 | X21: =IF($C21=YEAR(Model_Start_Date),1,X20*(1+O21)) -> 1.0365814 | Y21: =IF($C21=YEAR(Model_Start_Date),1,Y20*(1+P21)) -> 1.0553143 | Z21: =IF($C21=YEAR(Model_Start_Date),1,Z20*(1+Q21)) -> 1.0743475 | AA21: =IF($C21=YEAR(Model_Start_Date),1,AA20*(1+R21)) -> 1 | AB21: =IF($C21=YEAR(Model_Start_Date),1,AB20*(1+S21)) -> 1 | AC21: =IF($C21=YEAR(Model_Start_Date),1,AC20*(1+T21)) -> 1
B22: =B21+1 -> 11 | C22: =C21+1 -> 2035 | E22: % per year | F22: 0.02 | G22: =G$10*$F22 -> 0.004 | H22: =H$10*$F22 -> 0.006 | I22: =I$10*$F22 -> 0.008 | M22: % per year | N22: 0.02 | O22: 0.004 | P22: 0.006 | Q22: 0.008 | R22: 0 | S22: 0 | T22: 0 | V22: % per year | W22: =IF($C22=YEAR(Model_Start_Date),1,W21*(1+N22)) -> 1.2189944 | X22: =IF($C22=YEAR(Model_Start_Date),1,X21*(1+O22)) -> 1.0407277 | Y22: =IF($C22=YEAR(Model_Start_Date),1,Y21*(1+P22)) -> 1.0616462 | Z22: =IF($C22=YEAR(Model_Start_Date),1,Z21*(1+Q22)) -> 1.0829423 | AA22: =IF($C22=YEAR(Model_Start_Date),1,AA21*(1+R22)) -> 1 | AB22: =IF($C22=YEAR(Model_Start_Date),1,AB21*(1+S22)) -> 1 | AC22: =IF($C22=YEAR(Model_Start_Date),1,AC21*(1+T22)) -> 1
B23: =B22+1 -> 12 | C23: =C22+1 -> 2036 | E23: % per year | F23: 0.02 | G23: =G$10*$F23 -> 0.004 | H23: =H$10*$F23 -> 0.006 | I23: =I$10*$F23 -> 0.008 | M23: % per year | N23: 0.02 | O23: 0.004 | P23: 0.006 | Q23: 0.008 | R23: 0 | S23: 0 | T23: 0 | V23: % per year | W23: =IF($C23=YEAR(Model_Start_Date),1,W22*(1+N23)) -> 1.2433743 | X23: =IF($C23=YEAR(Model_Start_Date),1,X22*(1+O23)) -> 1.0448906 | Y23: =IF($C23=YEAR(Model_Start_Date),1,Y22*(1+P23)) -> 1.0680161 | Z23: =IF($C23=YEAR(Model_Start_Date),1,Z22*(1+Q23)) -> 1.0916058 | AA23: =IF($C23=YEAR(Model_Start_Date),1,AA22*(1+R23)) -> 1 | AB23: =IF($C23=YEAR(Model_Start_Date),1,AB22*(1+S23)) -> 1 | AC23: =IF($C23=YEAR(Model_Start_Date),1,AC22*(1+T23)) -> 1
B24: =B23+1 -> 13 | C24: =C23+1 -> 2037 | E24: % per year | F24: 0.02 | G24: =G$10*$F24 -> 0.004 | H24: =H$10*$F24 -> 0.006 | I24: =I$10*$F24 -> 0.008 | M24: % per year | N24: 0.02 | O24: 0.004 | P24: 0.006 | Q24: 0.008 | R24: 0 | S24: 0 | T24: 0 | V24: % per year | W24: =IF($C24=YEAR(Model_Start_Date),1,W23*(1+N24)) -> 1.2682418 | X24: =IF($C24=YEAR(Model_Start_Date),1,X23*(1+O24)) -> 1.0490702 | Y24: =IF($C24=YEAR(Model_Start_Date),1,Y23*(1+P24)) -> 1.0744242 | Z24: =IF($C24=YEAR(Model_Start_Date),1,Z23*(1+Q24)) -> 1.1003387 | AA24: =IF($C24=YEAR(Model_Start_Date),1,AA23*(1+R24)) -> 1 | AB24: =IF($C24=YEAR(Model_Start_Date),1,AB23*(1+S24)) -> 1 | AC24: =IF($C24=YEAR(Model_Start_Date),1,AC23*(1+T24)) -> 1
... B29: =B28+1 -> 18 | C29: =C28+1 -> 2042 | E29: % per year | F29: 0.02 | G29: =G$10*$F29 -> 0.004 | H29: =H$10*$F29 -> 0.006 | I29: =I$10*$F29 -> 0.008 | M29: % per year | N29: 0.02 | O29: 0.004 | P29: 0.006 | Q29: 0.008 | R29: 0 | S29: 0 | T29: 0 | V29: % per year | W29: =IF($C29=YEAR(Model_Start_Date),1,W28*(1+N29)) -> 1.4002414 | X29: =IF($C29=YEAR(Model_Start_Date),1,X28*(1+O29)) -> 1.0702201 | Y29: =IF($C29=YEAR(Model_Start_Date),1,Y28*(1+P29)) -> 1.107046 | Z29: =IF($C29=YEAR(Model_Start_Date),1,Z28*(1+Q29)) -> 1.1450621 | AA29: =IF($C29=YEAR(Model_Start_Date),1,AA28*(1+R29)) -> 1 | AB29: =IF($C29=YEAR(Model_Start_Date),1,AB28*(1+S29)) -> 1 | AC29: =IF($C29=YEAR(Model_Start_Date),1,AC28*(1+T29)) -> 1
A30: q | B30: =B29+1 -> 19 | C30: =C29+1 -> 2043 | E30: % per year | F30: 0.02 | G30: =G$10*$F30 -> 0.004 | H30: =H$10*$F30 -> 0.006 | I30: =I$10*$F30 -> 0.008 | M30: % per year | N30: 0.02 | O30: 0.004 | P30: 0.006 | Q30: 0.008 | R30: 0 | S30: 0 | T30: 0 | V30: % per year | W30: =IF($C30=YEAR(Model_Start_Date),1,W29*(1+N30)) -> 1.4282462 | X30: =IF($C30=YEAR(Model_Start_Date),1,X29*(1+O30)) -> 1.074501 | Y30: =IF($C30=YEAR(Model_Start_Date),1,Y29*(1+P30)) -> 1.1136883 | Z30: =IF($C30=YEAR(Model_Start_Date),1,Z29*(1+Q30)) -> 1.1542226 | AA30: =IF($C30=YEAR(Model_Start_Date),1,AA29*(1+R30)) -> 1 | AB30: =IF($C30=YEAR(Model_Start_Date),1,AB29*(1+S30)) -> 1 | AC30: =IF($C30=YEAR(Model_Start_Date),1,AC29*(1+T30)) -> 1
B31: =B30+1 -> 20 | C31: =C30+1 -> 2044 | E31: % per year | F31: 0.02 | G31: =G$10*$F31 -> 0.004 | H31: =H$10*$F31 -> 0.006 | I31: =I$10*$F31 -> 0.008 | M31: % per year | N31: 0.02 | O31: 0.004 | P31: 0.006 | Q31: 0.008 | R31: 0 | S31: 0 | T31: 0 | V31: % per year | W31: =IF($C31=YEAR(Model_Start_Date),1,W30*(1+N31)) -> 1.4568112 | X31: =IF($C31=YEAR(Model_Start_Date),1,X30*(1+O31)) -> 1.078799 | Y31: =IF($C31=YEAR(Model_Start_Date),1,Y30*(1+P31)) -> 1.1203704 | Z31: =IF($C31=YEAR(Model_Start_Date),1,Z30*(1+Q31)) -> 1.1634564 | AA31: =IF($C31=YEAR(Model_Start_Date),1,AA30*(1+R31)) -> 1 | AB31: =IF($C31=YEAR(Model_Start_Date),1,AB30*(1+S31)) -> 1 | AC31: =IF($C31=YEAR(Model_Start_Date),1,AC30*(1+T31)) -> 1
B32: =B31+1 -> 21 | C32: =C31+1 -> 2045 | E32: % per year | F32: 0.02 | G32: =G$10*$F32 -> 0.004 | H32: =H$10*$F32 -> 0.006 | I32: =I$10*$F32 -> 0.008 | M32: % per year | N32: 0.02 | O32: 0.004 | P32: 0.006 | Q32: 0.008 | R32: 0 | S32: 0 | T32: 0 | V32: % per year | W32: =IF($C32=YEAR(Model_Start_Date),1,W31*(1+N32)) -> 1.4859474 | X32: =IF($C32=YEAR(Model_Start_Date),1,X31*(1+O32)) -> 1.0831142 | Y32: =IF($C32=YEAR(Model_Start_Date),1,Y31*(1+P32)) -> 1.1270926 | Z32: =IF($C32=YEAR(Model_Start_Date),1,Z31*(1+Q32)) -> 1.172764 | AA32: =IF($C32=YEAR(Model_Start_Date),1,AA31*(1+R32)) -> 1 | AB32: =IF($C32=YEAR(Model_Start_Date),1,AB31*(1+S32)) -> 1 | AC32: =IF($C32=YEAR(Model_Start_Date),1,AC31*(1+T32)) -> 1
B33: =B32+1 -> 22 | C33: =C32+1 -> 2046 | E33: % per year | F33: 0.02 | G33: =G$10*$F33 -> 0.004 | H33: =H$10*$F33 -> 0.006 | I33: =I$10*$F33 -> 0.008 | M33: % per year | N33: 0.02 | O33: 0.004 | P33: 0.006 | Q33: 0.008 | R33: 0 | S33: 0 | T33: 0 | V33: % per year | W33: =IF($C33=YEAR(Model_Start_Date),1,W32*(1+N33)) -> 1.5156663 | X33: =IF($C33=YEAR(Model_Start_Date),1,X32*(1+O33)) -> 1.0874467 | Y33: =IF($C33=YEAR(Model_Start_Date),1,Y32*(1+P33)) -> 1.1338552 | Z33: =IF($C33=YEAR(Model_Start_Date),1,Z32*(1+Q33)) -> 1.1821462 | AA33: =IF($C33=YEAR(Model_Start_Date),1,AA32*(1+R33)) -> 1 | AB33: =IF($C33=YEAR(Model_Start_Date),1,AB32*(1+S33)) -> 1 | AC33: =IF($C33=YEAR(Model_Start_Date),1,AC32*(1+T33)) -> 1
B34: =B33+1 -> 23 | C34: =C33+1 -> 2047 | E34: % per year | F34: 0.02 | G34: =G$10*$F34 -> 0.004 | H34: =H$10*$F34 -> 0.006 | I34: =I$10*$F34 -> 0.008 | M34: % per year | N34: 0.02 | O34: 0.004 | P34: 0.006 | Q34: 0.008 | R34: 0 | S34: 0 | T34: 0 | V34: % per year | W34: =IF($C34=YEAR(Model_Start_Date),1,W33*(1+N34)) -> 1.5459797 | X34: =IF($C34=YEAR(Model_Start_Date),1,X33*(1+O34)) -> 1.0917965 | Y34: =IF($C34=YEAR(Model_Start_Date),1,Y33*(1+P34)) -> 1.1406583 | Z34: =IF($C34=YEAR(Model_Start_Date),1,Z33*(1+Q34)) -> 1.1916033 | AA34: =IF($C34=YEAR(Model_Start_Date),1,AA33*(1+R34)) -> 1 | AB34: =IF($C34=YEAR(Model_Start_Date),1,AB33*(1+S34)) -> 1 | AC34: =IF($C34=YEAR(Model_Start_Date),1,AC33*(1+T34)) -> 1
B35: =B34+1 -> 24 | C35: =C34+1 -> 2048 | E35: % per year | F35: 0.02 | G35: =G$10*$F35 -> 0.004 | H35: =H$10*$F35 -> 0.006 | I35: =I$10*$F35 -> 0.008 | M35: % per year | N35: 0.02 | O35: 0.004 | P35: 0.006 | Q35: 0.008 | R35: 0 | S35: 0 | T35: 0 | V35: % per year | W35: =IF($C35=YEAR(Model_Start_Date),1,W34*(1+N35)) -> 1.5768993 | X35: =IF($C35=YEAR(Model_Start_Date),1,X34*(1+O35)) -> 1.0961636 | Y35: =IF($C35=YEAR(Model_Start_Date),1,Y34*(1+P35)) -> 1.1475023 | Z35: =IF($C35=YEAR(Model_Start_Date),1,Z34*(1+Q35)) -> 1.2011362 | AA35: =IF($C35=YEAR(Model_Start_Date),1,AA34*(1+R35)) -> 1 | AB35: =IF($C35=YEAR(Model_Start_Date),1,AB34*(1+S35)) -> 1 | AC35: =IF($C35=YEAR(Model_Start_Date),1,AC34*(1+T35)) -> 1
B36: =B35+1 -> 25 | C36: =C35+1 -> 2049 | E36: % per year | F36: 0.02 | G36: =G$10*$F36 -> 0.004 | H36: =H$10*$F36 -> 0.006 | I36: =I$10*$F36 -> 0.008 | M36: % per year | N36: 0.02 | O36: 0.004 | P36: 0.006 | Q36: 0.008 | R36: 0 | S36: 0 | T36: 0 | V36: % per year | W36: =IF($C36=YEAR(Model_Start_Date),1,W35*(1+N36)) -> 1.6084372 | X36: =IF($C36=YEAR(Model_Start_Date),1,X35*(1+O36)) -> 1.1005483 | Y36: =IF($C36=YEAR(Model_Start_Date),1,Y35*(1+P36)) -> 1.1543873 | Z36: =IF($C36=YEAR(Model_Start_Date),1,Z35*(1+Q36)) -> 1.2107452 | AA36: =IF($C36=YEAR(Model_Start_Date),1,AA35*(1+R36)) -> 1 | AB36: =IF($C36=YEAR(Model_Start_Date),1,AB35*(1+S36)) -> 1 | AC36: =IF($C36=YEAR(Model_Start_Date),1,AC35*(1+T36)) -> 1
B37: =B36+1 -> 26 | C37: =C36+1 -> 2050 | E37: % per year | F37: 0.02 | G37: =G$10*$F37 -> 0.004 | H37: =H$10*$F37 -> 0.006 | I37: =I$10*$F37 -> 0.008 | M37: % per year | N37: 0.02 | O37: 0.004 | P37: 0.006 | Q37: 0.008 | R37: 0 | S37: 0 | T37: 0 | V37: % per year | W37: =IF($C37=YEAR(Model_Start_Date),1,W36*(1+N37)) -> 1.640606 | X37: =IF($C37=YEAR(Model_Start_Date),1,X36*(1+O37)) -> 1.1049505 | Y37: =IF($C37=YEAR(Model_Start_Date),1,Y36*(1+P37)) -> 1.1613136 | Z37: =IF($C37=YEAR(Model_Start_Date),1,Z36*(1+Q37)) -> 1.2204312 | AA37: =IF($C37=YEAR(Model_Start_Date),1,AA36*(1+R37)) -> 1 | AB37: =IF($C37=YEAR(Model_Start_Date),1,AB36*(1+S37)) -> 1 | AC37: =IF($C37=YEAR(Model_Start_Date),1,AC36*(1+T37)) -> 1
B38: =B37+1 -> 27 | C38: =C37+1 -> 2051 | E38: % per year | F38: 0.02 | G38: =G$10*$F38 -> 0.004 | H38: =H$10*$F38 -> 0.006 | I38: =I$10*$F38 -> 0.008 | M38: % per year | N38: 0.02 | O38: 0.004 | P38: 0.006 | Q38: 0.008 | R38: 0 | S38: 0 | T38: 0 | V38: % per year | W38: =IF($C38=YEAR(Model_Start_Date),1,W37*(1+N38)) -> 1.6734181 | X38: =IF($C38=YEAR(Model_Start_Date),1,X37*(1+O38)) -> 1.1093703 | Y38: =IF($C38=YEAR(Model_Start_Date),1,Y37*(1+P38)) -> 1.1682815 | Z38: =IF($C38=YEAR(Model_Start_Date),1,Z37*(1+Q38)) -> 1.2301947 | AA38: =IF($C38=YEAR(Model_Start_Date),1,AA37*(1+R38)) -> 1 | AB38: =IF($C38=YEAR(Model_Start_Date),1,AB37*(1+S38)) -> 1 | AC38: =IF($C38=YEAR(Model_Start_Date),1,AC37*(1+T38)) -> 1
B39: =B38+1 -> 28 | C39: =C38+1 -> 2052 | E39: % per year | F39: 0.02 | G39: =G$10*$F39 -> 0.004 | H39: =H$10*$F39 -> 0.006 | I39: =I$10*$F39 -> 0.008 | M39: % per year | N39: 0.02 | O39: 0.004 | P39: 0.006 | Q39: 0.008 | R39: 0 | S39: 0 | T39: 0 | V39: % per year | W39: =IF($C39=YEAR(Model_Start_Date),1,W38*(1+N39)) -> 1.7068865 | X39: =IF($C39=YEAR(Model_Start_Date),1,X38*(1+O39)) -> 1.1138078 | Y39: =IF($C39=YEAR(Model_Start_Date),1,Y38*(1+P39)) -> 1.1752912 | Z39: =IF($C39=YEAR(Model_Start_Date),1,Z38*(1+Q39)) -> 1.2400362 | AA39: =IF($C39=YEAR(Model_Start_Date),1,AA38*(1+R39)) -> 1 | AB39: =IF($C39=YEAR(Model_Start_Date),1,AB38*(1+S39)) -> 1 | AC39: =IF($C39=YEAR(Model_Start_Date),1,AC38*(1+T39)) -> 1
B40: =B39+1 -> 29 | C40: =C39+1 -> 2053 | E40: % per year | F40: 0.02 | G40: =G$10*$F40 -> 0.004 | H40: =H$10*$F40 -> 0.006 | I40: =I$10*$F40 -> 0.008 | M40: % per year | N40: 0.02 | O40: 0.004 | P40: 0.006 | Q40: 0.008 | R40: 0 | S40: 0 | T40: 0 | V40: % per year | W40: =IF($C40=YEAR(Model_Start_Date),1,W39*(1+N40)) -> 1.7410242 | X40: =IF($C40=YEAR(Model_Start_Date),1,X39*(1+O40)) -> 1.118263 | Y40: =IF($C40=YEAR(Model_Start_Date),1,Y39*(1+P40)) -> 1.1823429 | Z40: =IF($C40=YEAR(Model_Start_Date),1,Z39*(1+Q40)) -> 1.2499565 | AA40: =IF($C40=YEAR(Model_Start_Date),1,AA39*(1+R40)) -> 1 | AB40: =IF($C40=YEAR(Model_Start_Date),1,AB39*(1+S40)) -> 1 | AC40: =IF($C40=YEAR(Model_Start_Date),1,AC39*(1+T40)) -> 1
B41: =B40+1 -> 30 | C41: =C40+1 -> 2054 | E41: % per year | F41: 0.02 | G41: =G$10*$F41 -> 0.004 | H41: =H$10*$F41 -> 0.006 | I41: =I$10*$F41 -> 0.008 | M41: % per year | N41: 0.02 | O41: 0.004 | P41: 0.006 | Q41: 0.008 | R41: 0 | S41: 0 | T41: 0 | V41: % per year | W41: =IF($C41=YEAR(Model_Start_Date),1,W40*(1+N41)) -> 1.7758447 | X41: =IF($C41=YEAR(Model_Start_Date),1,X40*(1+O41)) -> 1.1227361 | Y41: =IF($C41=YEAR(Model_Start_Date),1,Y40*(1+P41)) -> 1.189437 | Z41: =IF($C41=YEAR(Model_Start_Date),1,Z40*(1+Q41)) -> 1.2599562 | AA41: =IF($C41=YEAR(Model_Start_Date),1,AA40*(1+R41)) -> 1 | AB41: =IF($C41=YEAR(Model_Start_Date),1,AB40*(1+S41)) -> 1 | AC41: =IF($C41=YEAR(Model_Start_Date),1,AC40*(1+T41)) -> 1
B42: =B41+1 -> 31 | C42: =C41+1 -> 2055 | E42: % per year | F42: 0.02 | G42: =G$10*$F42 -> 0.004 | H42: =H$10*$F42 -> 0.006 | I42: =I$10*$F42 -> 0.008 | M42: % per year | N42: 0.02 | O42: 0.004 | P42: 0.006 | Q42: 0.008 | R42: 0 | S42: 0 | T42: 0 | V42: % per year | W42: =IF($C42=YEAR(Model_Start_Date),1,W41*(1+N42)) -> 1.8113616 | X42: =IF($C42=YEAR(Model_Start_Date),1,X41*(1+O42)) -> 1.127227 | Y42: =IF($C42=YEAR(Model_Start_Date),1,Y41*(1+P42)) -> 1.1965736 | Z42: =IF($C42=YEAR(Model_Start_Date),1,Z41*(1+Q42)) -> 1.2700358 | AA42: =IF($C42=YEAR(Model_Start_Date),1,AA41*(1+R42)) -> 1 | AB42: =IF($C42=YEAR(Model_Start_Date),1,AB41*(1+S42)) -> 1 | AC42: =IF($C42=YEAR(Model_Start_Date),1,AC41*(1+T42)) -> 1
... B62: =B61+1 -> 51 | C62: =C61+1 -> 2075 | E62: % per year | F62: 0.02 | G62: =G$10*$F62 -> 0.004 | H62: =H$10*$F62 -> 0.006 | I62: =I$10*$F62 -> 0.008 | M62: % per year | N62: 0.02 | O62: 0.004 | P62: 0.006 | Q62: 0.008 | R62: 0 | S62: 0 | T62: 0 | V62: % per year | W62: =IF($C62=YEAR(Model_Start_Date),1,W61*(1+N62)) -> 2.691588 | X62: =IF($C62=YEAR(Model_Start_Date),1,X61*(1+O62)) -> 1.2209156 | Y62: =IF($C62=YEAR(Model_Start_Date),1,Y61*(1+P62)) -> 1.3486493 | Z62: =IF($C62=YEAR(Model_Start_Date),1,Z61*(1+Q62)) -> 1.4894523 | AA62: =IF($C62=YEAR(Model_Start_Date),1,AA61*(1+R62)) -> 1 | AB62: =IF($C62=YEAR(Model_Start_Date),1,AB61*(1+S62)) -> 1 | AC62: =IF($C62=YEAR(Model_Start_Date),1,AC61*(1+T62)) -> 1
A63: MARKET_IPC_YEAR_STOP | B63: =B62+1 -> 52 | C63: =C62+1 -> 2076 | E63: % per year | F63: 0.02 | G63: =G$10*$F63 -> 0.004 | H63: =H$10*$F63 -> 0.006 | I63: =I$10*$F63 -> 0.008 | M63: % per year | N63: 0.02 | O63: 0.004 | P63: 0.006 | Q63: 0.008 | R63: 0 | S63: 0 | T63: 0 | V63: % per year | W63: =IF($C63=YEAR(Model_Start_Date),1,W62*(1+N63)) -> 2.7454198 | X63: =IF($C63=YEAR(Model_Start_Date),1,X62*(1+O63)) -> 1.2257993 | Y63: =IF($C63=YEAR(Model_Start_Date),1,Y62*(1+P63)) -> 1.3567412 | Z63: =IF($C63=YEAR(Model_Start_Date),1,Z62*(1+Q63)) -> 1.5013679 | AA63: =IF($C63=YEAR(Model_Start_Date),1,AA62*(1+R63)) -> 1 | AB63: =IF($C63=YEAR(Model_Start_Date),1,AB62*(1+S63)) -> 1 | AC63: =IF($C63=YEAR(Model_Start_Date),1,AC62*(1+T63)) -> 1
B70: =B6+1 -> 2 | C70: MARKET PRICES
I72: FORECASTS | O72: AURORA Q1
A73: MARKET_PRICE_SCENARIO | I73: Market price scenario | N73: Flat price dashboard | O73: Low captured | P73: Mid captured | Q73: 30 €/MWh | R73: 0 €/MWh | S73: 50 €/MWh | T73: Low non indexed | V73: 70%Mid/30%Low | W73: 80%Mid/20%Low
H75: ref | I75: Year
H76: 1 | I76: =C12 -> 2025 | M76: € / MWh | N76: =Dashboard!T139 -> 0 | O76: 37.117532 | P76: 58.237931 | Q76: 30 | S76: 50 | T76: 43.6 | V76: =70%*P76+30%*O76 -> 51.901811 | W76: =80%*P76+20%*O76 -> 54.013851 | AU76: 44.578422 | AV76: 45.46999 | AW76: 46.37939 | AX76: 47.306978 | AY76: 48.253117 | AZ76: 49.21818 | BA76: 50.202543 | BB76: 51.206594 | BC76: 52.230726 | BD76: 53.275341 | BE76: 54.340848 | BF76: 55.427664 | BG76: 56.536218 | BH76: 57.666942 | BI76: 58.820281 | BJ76: 59.996687 | BK76: 61.19662 | BL76: 62.420553 | BM76: 63.668964 | BN76: 64.942343
H77: =H76+1 -> 2 | I77: =I76+1 -> 2026 | M77: € / MWh | N77: =N76 -> 0 | O77: 30.487446 | P77: 45.51797 | Q77: 30.6 | S77: =S76 -> 50 | T77: 36.3 | V77: =70%*P77+30%*O77 -> 41.008813 | W77: =80%*P77+20%*O77 -> 42.511865
H78: =H77+1 -> 3 | I78: =I77+1 -> 2027 | M78: € / MWh | N78: =N77 -> 0 | O78: 26.839817 | P78: 38.140793 | Q78: 31.212 | S78: =S77 -> 50 | T78: 30.96 | V78: =70%*P78+30%*O78 -> 34.7505 | W78: =80%*P78+20%*O78 -> 35.880598
H79: =H78+1 -> 4 | I79: =I78+1 -> 2028 | M79: € / MWh | N79: =N78 -> 0 | O79: 28.690046 | P79: 39.10265 | Q79: 31.83624 | S79: =S78 -> 50 | T79: 30.16 | V79: =70%*P79+30%*O79 -> 35.978869 | W79: =80%*P79+20%*O79 -> 37.020129
H80: =H79+1 -> 5 | I80: =I79+1 -> 2029 | M80: € / MWh | N80: =N79 -> 0 | O80: 33.534684 | P80: 46.97114 | Q80: 32.472965 | S80: =S79 -> 50 | T80: 32.51 | V80: =70%*P80+30%*O80 -> 42.940203 | W80: =80%*P80+20%*O80 -> 44.283849
H81: =H80+1 -> 6 | I81: =I80+1 -> 2030 | M81: € / MWh | N81: =N80 -> 0 | O81: 37.775636 | P81: 52.402178 | Q81: 33.122424 | S81: =S80 -> 50 | T81: 34.83 | V81: =70%*P81+30%*O81 -> 48.014216 | W81: =80%*P81+20%*O81 -> 49.47687
H82: =H81+1 -> 7 | I82: =I81+1 -> 2031 | M82: € / MWh | N82: =N81 -> 0 | O82: 41.937866 | P82: 57.914197 | Q82: 33.784873 | S82: =S81 -> 50 | T82: 37.19 | V82: =70%*P82+30%*O82 -> 53.121298 | W82: =80%*P82+20%*O82 -> 54.718931
H83: =H82+1 -> 8 | I83: =I82+1 -> 2032 | M83: € / MWh | N83: =N82 -> 0 | O83: 42.896446 | P83: 59.07248 | Q83: 34.46057 | S83: =S82 -> 50 | T83: 36.54 | V83: =70%*P83+30%*O83 -> 54.21967 | W83: =80%*P83+20%*O83 -> 55.837274
H84: =H83+1 -> 9 | I84: =I83+1 -> 2033 | M84: € / MWh | N84: =N83 -> 0 | O84: 44.732127 | P84: 61.476119 | Q84: 35.149781 | S84: =S83 -> 50 | T84: 36.3 | V84: =70%*P84+30%*O84 -> 56.452922 | W84: =80%*P84+20%*O84 -> 58.127321
H85: =H84+1 -> 10 | I85: =I84+1 -> 2034 | M85: € / MWh | N85: =N84 -> 0 | O85: 46.499412 | P85: 63.578285 | Q85: 35.852777 | S85: =S84 -> 50 | T85: 37.67 | V85: =70%*P85+30%*O85 -> 58.454623 | W85: =80%*P85+20%*O85 -> 60.16251
H86: =H85+1 -> 11 | I86: =I85+1 -> 2035 | M86: € / MWh | N86: =N85 -> 0 | O86: 47.556557 | P86: 63.832598 | Q86: 36.569833 | S86: =S85 -> 50 | T86: 39.14 | V86: =70%*P86+30%*O86 -> 58.949786 | W86: =80%*P86+20%*O86 -> 60.57739
H87: =H86+1 -> 12 | I87: =I86+1 -> 2036 | M87: € / MWh | N87: =N86 -> 0 | O87: 53.176877 | P87: 71.334836 | Q87: 37.301229 | S87: =S86 -> 50 | T87: 41.68 | V87: =70%*P87+30%*O87 -> 65.887448 | W87: =80%*P87+20%*O87 -> 67.703244
H88: =H87+1 -> 13 | I88: =I87+1 -> 2037 | M88: € / MWh | N88: =N87 -> 0 | O88: 53.049772 | P88: 68.925015 | Q88: 38.047254 | S88: =S87 -> 50 | T88: 42.69 | V88: =70%*P88+30%*O88 -> 64.162442 | W88: =80%*P88+20%*O88 -> 65.749966
... H115: =H114+1 -> 40 | I115: =I114+1 -> 2064 | M115: € / MWh | N115: =N114 -> 0 | O115: 68.63395 | P115: 87.409195 | Q115: 64.942343 | S115: =S114 -> 50 | T115: 32.9 | V115: =70%*P115+30%*O115 -> 81.776622 | W115: =80%*P115+20%*O115 -> 83.654146
H116: =H115+1 -> 41 | I116: =I115+1 -> 2065 | M116: € / MWh | N116: =N115 -> 0 | O116: 68.63395 | P116: 87.409195 | Q116: =Q115 -> 64.942343 | S116: =S115 -> 50 | T116: 32.9 | V116: =70%*P116+30%*O116 -> 81.776622 | W116: =80%*P116+20%*O116 -> 83.654146
H117: =H116+1 -> 42 | I117: =I116+1 -> 2066 | M117: € / MWh | N117: =N116 -> 0 | O117: 68.63395 | P117: 87.409195 | Q117: =Q116 -> 64.942343 | S117: =S116 -> 50 | T117: 32.9 | V117: =70%*P117+30%*O117 -> 81.776622 | W117: =80%*P117+20%*O117 -> 83.654146
H118: =H117+1 -> 43 | I118: =I117+1 -> 2067 | M118: € / MWh | N118: =N117 -> 0 | O118: 68.63395 | P118: 87.409195 | Q118: =Q117 -> 64.942343 | S118: =S117 -> 50 | T118: 32.9 | V118: =70%*P118+30%*O118 -> 81.776622 | W118: =80%*P118+20%*O118 -> 83.654146
H119: =H118+1 -> 44 | I119: =I118+1 -> 2068 | M119: € / MWh | N119: =N118 -> 0 | O119: 68.63395 | P119: 87.409195 | Q119: =Q118 -> 64.942343 | S119: =S118 -> 50 | T119: 32.9 | V119: =70%*P119+30%*O119 -> 81.776622 | W119: =80%*P119+20%*O119 -> 83.654146
H120: =H119+1 -> 45 | I120: =I119+1 -> 2069 | M120: € / MWh | N120: =N119 -> 0 | O120: 68.63395 | P120: 87.409195 | Q120: =Q119 -> 64.942343 | S120: =S119 -> 50 | T120: 32.9 | V120: =70%*P120+30%*O120 -> 81.776622 | W120: =80%*P120+20%*O120 -> 83.654146
H121: =H120+1 -> 46 | I121: =I120+1 -> 2070 | M121: € / MWh | N121: =N120 -> 0 | O121: 68.63395 | P121: 87.409195 | Q121: =Q120 -> 64.942343 | S121: =S120 -> 50 | T121: 32.9 | V121: =70%*P121+30%*O121 -> 81.776622 | W121: =80%*P121+20%*O121 -> 83.654146
H122: =H121+1 -> 47 | I122: =I121+1 -> 2071 | M122: € / MWh | N122: =N121 -> 0 | O122: 68.63395 | P122: 87.409195 | Q122: =Q121 -> 64.942343 | S122: =S121 -> 50 | T122: 32.9 | V122: =70%*P122+30%*O122 -> 81.776622 | W122: =80%*P122+20%*O122 -> 83.654146
H123: =H122+1 -> 48 | I123: =I122+1 -> 2072 | M123: € / MWh | N123: =N122 -> 0 | O123: 68.63395 | P123: 87.409195 | Q123: =Q122 -> 64.942343 | S123: =S122 -> 50 | T123: 32.9 | V123: =70%*P123+30%*O123 -> 81.776622 | W123: =80%*P123+20%*O123 -> 83.654146
H124: =H123+1 -> 49 | I124: =I123+1 -> 2073 | M124: € / MWh | N124: =N123 -> 0 | O124: 68.63395 | P124: 87.409195 | Q124: =Q123 -> 64.942343 | S124: =S123 -> 50 | T124: 32.9 | V124: =70%*P124+30%*O124 -> 81.776622 | W124: =80%*P124+20%*O124 -> 83.654146
H125: =H124+1 -> 50 | I125: =I124+1 -> 2074 | M125: € / MWh | N125: =N124 -> 0 | O125: 68.63395 | P125: 87.409195 | Q125: =Q124 -> 64.942343 | S125: =S124 -> 50 | T125: 32.9 | V125: =70%*P125+30%*O125 -> 81.776622 | W125: =80%*P125+20%*O125 -> 83.654146
H126: =H125+1 -> 51 | I126: =I125+1 -> 2075 | M126: € / MWh | N126: =N125 -> 0 | O126: 68.63395 | P126: 87.409195 | Q126: =Q125 -> 64.942343 | S126: =S125 -> 50 | T126: 32.9 | V126: =70%*P126+30%*O126 -> 81.776622 | W126: =80%*P126+20%*O126 -> 83.654146
H127: =H126+1 -> 52 | I127: =I126+1 -> 2076 | M127: € / MWh | N127: =N126 -> 0 | O127: 68.63395 | P127: 87.409195 | Q127: =Q126 -> 64.942343 | S127: =S126 -> 50 | T127: 32.9 | V127: =70%*P127+30%*O127 -> 81.776622 | W127: =80%*P127+20%*O127 -> 83.654146
B129: =B70+1 -> 3 | C129: EURIBOR
C131: INDEX | H131: E1M | I131: E3M | J131: E6M | N131: {=H131:J131} -> E1M | O131: E3M | P131: E6M
C133: Date BoP | E133: Date EoP
B134: date | C134: =Model_Start_Date -> 45658 | E134: =EOMONTH(C134,0) -> 45688 | G134: % | I134: 0.026145 | J134: 0.026145 | M134: % | N134: {=IF(sensi=1,$H$134:$J$633+Dashboard!$U$139,$H$134:$J$633)} -> 0 | O134: 0.026145 | P134: 0.026145
B135: date | C135: =E134+1 -> 45689 | E135: =EOMONTH(C135,0) -> 45716 | G135: % | I135: 0.026145 | J135: 0.026145 | M135: % | N135: 0 | O135: 0.026145 | P135: 0.026145
B136: date | C136: =E135+1 -> 45717 | E136: =EOMONTH(C136,0) -> 45747 | G136: % | I136: 0.026145 | J136: 0.026145 | M136: % | N136: 0 | O136: 0.026145 | P136: 0.026145
B137: date | C137: =E136+1 -> 45748 | E137: =EOMONTH(C137,0) -> 45777 | G137: % | I137: 0.026145 | J137: 0.026145 | M137: % | N137: 0 | O137: 0.026145 | P137: 0.026145
B138: date | C138: =E137+1 -> 45778 | E138: =EOMONTH(C138,0) -> 45808 | G138: % | I138: 0.026145 | J138: 0.026145 | M138: % | N138: 0 | O138: 0.026145 | P138: 0.026145
B139: date | C139: =E138+1 -> 45809 | E139: =EOMONTH(C139,0) -> 45838 | G139: % | I139: 0.026145 | J139: 0.026145 | M139: % | N139: 0 | O139: 0.026145 | P139: 0.026145
B140: date | C140: =E139+1 -> 45839 | E140: =EOMONTH(C140,0) -> 45869 | G140: % | I140: 0.026145 | J140: 0.026145 | M140: % | N140: 0 | O140: 0.026145 | P140: 0.026145
B141: date | C141: =E140+1 -> 45870 | E141: =EOMONTH(C141,0) -> 45900 | G141: % | I141: 0.026145 | J141: 0.026145 | M141: % | N141: 0 | O141: 0.026145 | P141: 0.026145
B142: date | C142: =E141+1 -> 45901 | E142: =EOMONTH(C142,0) -> 45930 | G142: % | I142: 0.026145 | J142: 0.026145 | M142: % | N142: 0 | O142: 0.026145 | P142: 0.026145
B143: date | C143: =E142+1 -> 45931 | E143: =EOMONTH(C143,0) -> 45961 | G143: % | I143: 0.026145 | J143: 0.026145 | M143: % | N143: 0 | O143: 0.026145 | P143: 0.026145
B144: date | C144: =E143+1 -> 45962 | E144: =EOMONTH(C144,0) -> 45991 | G144: % | I144: 0.026145 | J144: 0.026145 | M144: % | N144: 0 | O144: 0.026145 | P144: 0.026145
B145: date | C145: =E144+1 -> 45992 | E145: =EOMONTH(C145,0) -> 46022 | G145: % | I145: 0.026145 | J145: 0.026145 | M145: % | N145: 0 | O145: 0.026145 | P145: 0.026145
B146: date | C146: =E145+1 -> 46023 | E146: =EOMONTH(C146,0) -> 46053 | G146: % | I146: 0.026145 | J146: 0.026145 | M146: % | N146: 0 | O146: 0.026145 | P146: 0.026145
... B633: date | C633: =E632+1 -> 60845 | E633: =EOMONTH(C633,0) -> 60875 | G633: % | I633: 0.026145 | J633: 0.026145 | M633: % | N633: 0 | O633: 0.026145 | P633: 0.026145
B635: =B129+1 -> 4 | C635: END
I637: =I636 -> 0
I638: =I637 -> 0
I639: =I638 -> 0
I640: =I639 -> 0
I641: =I640 -> 0
I642: =I641 -> 0
I643: =I642 -> 0
I644: =I643 -> 0
I645: =I644 -> 0
I646: =I645 -> 0
I647: =I646 -> 0
I648: =I647 -> 0
... I693: =I692 -> 0

Sheet ass_Asset
A2: ASSET_CODE | C2: Vehicle | K2: list | M2: SPV_1 | N2: SPV_2 | O2: SPV_3 | P2: SPV_3 | Q2: SPV_42
A3: ASSET_NAME | C3: Asset name | K3: name | M3: Actif_1 | N3: Actif_2 | O3: Actif_3 | P3: Actif_4 | Q3: Actif_does_not_exist
A4: ASSET_TYPE | C4: Asset type | K4: list | M4: Solar | N4: Solar | O4: Solar | P4: Solar | Q4: nimp
C5: Contract type | K5: contract | M5: =IF(M16,IF(M53=TRUE(),"Self-consumption","PPA"),"") -> PPA | N5: =IF(N16,IF(N53=TRUE(),"Self-consumption","PPA"),"") | O5: =IF(O16,IF(O53=TRUE(),"Self-consumption","PPA"),"") -> PPA | P5: =IF(P16,IF(P53=TRUE(),"Self-consumption","PPA"),"") -> PPA
C6: Phase | K6: phase | M6: =M27 -> 1 | N6: =N27 -> 1 | O6: =O27 -> 1 | P6: =P27 -> 1
C7: ref Asset | K7: ref_Asset | M7: =L7+1 -> 1 | N7: =M7+1 -> 2 | O7: =N7+1 -> 3 | P7: =O7+1 -> 4
C8: ref Vehicle | K8: ref_Vehicle | M8: =IFERROR(MATCH(M2,#REF!,0),"") | N8: =IFERROR(MATCH(N2,#REF!,0),"") | O8: =IFERROR(MATCH(O2,#REF!,0),"") | P8: =IFERROR(MATCH(P2,#REF!,0),"")
C9: ref Perimeter (senior facility) | K9: ref_Perimeter (senior facility) | M9: =IFERROR(IF(M16,INDEX(#REF!,,M8),""),"") | N9: =IFERROR(IF(N16,INDEX(#REF!,,N8),""),"") | O9: =IFERROR(IF(O16,INDEX(#REF!,,O8),""),"") | P9: =IFERROR(IF(P16,INDEX(#REF!,,P8),""),"")
A10: ASSET_TYPOLOGY | C10: Asset typology | K10: ref_Typo | M10: BAT | N10: SOL | O10: BAT | P10: OMBRIERE
B12: =1 -> 1 | C12: ASSET ACTIVATION
A14: ASSET_MASTER_ACTIVATION | C14: Master asset activation | F14: Number of assets | H14: =COUNTIF(M14:O14,TRUE()) -> 2 | K14: VRAI/FAUX | M14: =TRUE() -> TRUE | N14: =FALSE() -> FALSE | O14: =TRUE() -> TRUE | P14: =TRUE() -> TRUE | Q14: FALSE
C15: Phase activation | K15: VRAI/FAUX | M15: =TRUE() -> TRUE | N15: =FALSE() -> FALSE | O15: =TRUE() -> TRUE | P15: =TRUE() -> TRUE
A16: ASSET_ACTIVATION | C16: Asset activation | F16: Number of assets | H16: =COUNTIF(M16:O16,TRUE()) -> 2 | K16: VRAI/FAUX | M16: =AND(M14,M15) -> TRUE | N16: =FALSE() -> FALSE | O16: =AND(O14,O15) -> TRUE | P16: =AND(P14,P15) -> TRUE
B18: =B12+1 -> 2 | C18: TIMELINE
C20: Sensitives | F20: Asset life in sensitive | G20: Part of Assets in perimeter (senior facility) | I20: Activation
C21: Asset life in sensitive for 5% of portfolio | E21: months | F21: =IF($I$21,Dashboard!$AA$139,0) -> 0 | G21: =SUMPRODUCT(M21:O21,$M$426:$O$426) -> 0 | H21: VRAI/FAUX | I21: =IF(sensi=1,Dashboard!$Z$139,FALSE()) -> 0 | K21: 1/0
C22: Asset desactivation @CoD | G22: =SUMPRODUCT(M22:O22,$M$426:$O$426) -> 0 | H22: VRAI/FAUX | I22: =IF(sensi=1,Dashboard!$AB$139,FALSE()) -> 0 | K22: 1/0
C24: CONSTRUCTION
A25: ASSET_CONSTRUCTION_START | C25: Construction start | K25: date | M25: 45742 | N25: 45808 | O25: 45808 | P25: 45808
A26: ASSET_CONSTRUCTION_END | C26: Construction end | K26: date | M26: 46106 | N26: 46172 | O26: 46172 | P26: 46172
C27: Activated construction phase | K27: phase | M27: 1 | N27: 1 | O27: 1 | P27: 1
C29: OPERATING
A30: ASSET_MERCHANT_PRE_CONTRACT_START | C30: Merchant pre contracted start | K30: date | M30: =IF(M$16=TRUE(),M26+1,) -> 46107 | N30: =IF(N$16=TRUE(),N26+1,) -> 0 | O30: =IF(O$16=TRUE(),O26+1,) -> 46173 | P30: =IF(P$16=TRUE(),P26+1,) -> 46173
C31: Merchant pre contracted duration | K31: months
A32: ASSET_MERCHANT_PRE_CONTRACT_END | C32: Merchant pre contracted end | K32: date | M32: =M30+45 -> 46152 | N32: =IF(N$16=TRUE(),IF(N31>0,EDATE(N30,N31)-1,N30-1),) -> 0 | O32: =O30+45 -> 46218 | P32: =P30+45 -> 46218
A33: ASSET_OPERATION_CONTRACT_START | C33: Contract start | K33: date | M33: =IF(M$16=TRUE(),M32+1,) -> 46153 | N33: =IF(N$16=TRUE(),N32+1,) -> 0 | O33: =IF(O$16=TRUE(),O32+1,) -> 46219 | P33: =IF(P$16=TRUE(),P32+1,) -> 46219
C34: Contract duration | K34: months | M34: 240 | N34: 240 | O34: 240 | P34: 240
C35: Contract duration | K35: months | M35: =IF(AND($I$21,M$21=1),$F$21,M$34) -> 240 | N35: =IF(AND($I$21,N$21=1),$F$21,N$34) -> 240 | O35: =IF(AND($I$21,O$21=1),$F$21,O$34) -> 240 | P35: =IF(AND($I$21,P$21=1),$F$21,P$34) -> 240
A36: ASSET_OPERATION_CONTRACT_END | C36: Contract end | K36: date | M36: =IF(M$16=TRUE(),IF(M35>0,EDATE(M33,M35)-1,M33-1),) -> 53457 | N36: =IF(N$16=TRUE(),IF(N35>0,EDATE(N33,N35)-1,N33-1),) -> 0 | O36: =IF(O$16=TRUE(),IF(O35>0,EDATE(O33,O35)-1,O33-1),) -> 53523 | P36: =IF(P$16=TRUE(),IF(P35>0,EDATE(P33,P35)-1,P33-1),) -> 53523
A37: ASSET_MERCHANT_POST_CONTRACT_START | C37: Merchant start post contracted | K37: date | M37: =IF(M$16=TRUE(),M36+1,) -> 53458 | N37: =IF(N$16=TRUE(),N36+1,) -> 0 | O37: =IF(O$16=TRUE(),O36+1,) -> 53524 | P37: =IF(P$16=TRUE(),P36+1,) -> 53524
C38: Merchant period | K38: months | M38: =IF(M$16=TRUE(),IF(AND(sensi=1,$I$21=TRUE(),M21=1),0,IF(AND(sensi=1,scenario=1,Dashboard!$Y$139<>0),Dashboard!$Y$139-M35,INDEX(M41:M42,scenario,))),) -> #REF! | N38: =IF(N$16=TRUE(),IF(AND(sensi=1,$I$21=TRUE(),N21=1),0,IF(AND(sensi=1,scenario=1,Dashboard!$Y$139<>0),Dashboard!$Y$139-N35,INDEX(N41:N42,scenario,))),) -> 0 | O38: =IF(O$16=TRUE(),IF(AND(sensi=1,$I$21=TRUE(),O21=1),0,IF(AND(sensi=1,scenario=1,Dashboard!$Y$139<>0),Dashboard!$Y$139-O35,INDEX(O41:O42,scenario,))),) -> #REF! | P38: =IF(P$16=TRUE(),IF(AND(sensi=1,$I$21=TRUE(),P21=1),0,IF(AND(sensi=1,scenario=1,Dashboard!$Y$139<>0),Dashboard!$Y$139-P35,INDEX(P41:P42,scenario,))),) -> #REF!
A39: ASSET_MERCHANT_POST_CONTRACT_END | C39: End of merchant post contracted | K39: date | M39: =M37+2000 -> 55458 | N39: =IF(N$16=TRUE(),IF(N38>0,EDATE(N37,N38)-1,N37-1),) -> 0 | O39: =O37+2000 -> 55524 | P39: =P37+2000 -> 55524
C41: Merchant period - lenders | K41: months | M41: =IF(M16,INDEX(#REF!,,M9),) -> #VALUE! | N41: =IF(N16,INDEX(#REF!,,N9),) -> 0 | O41: =IF(O16,INDEX(#REF!,,O9),) -> #VALUE! | P41: =IF(P16,INDEX(#REF!,,P9),) -> #VALUE!
C42: Merchant period - sponsor | K42: months | M42: 120 | N42: 120 | O42: 120 | P42: 120
C43: End of merchant post contracted - lenders | K43: date | M43: =IF(M$16=TRUE(),IF(M$41>0,EDATE(M$37,IF(sensi=1,IF(AND(M$21=1,$I$21),0,M$41+Dashboard!$Y$139),M$41))-1,M$37-1),) -> #VALUE! | N43: =IF(N$16=TRUE(),IF(N$41>0,EDATE(N$37,IF(sensi=1,IF(AND(N$21=1,$I$21),0,N$41+Dashboard!$Y$139),N$41))-1,N$37-1),) -> 0 | O43: =IF(O$16=TRUE(),IF(O$41>0,EDATE(O$37,IF(sensi=1,IF(AND(O$21=1,$I$21),0,O$41+Dashboard!$Y$139),O$41))-1,O$37-1),) -> #VALUE! | P43: =IF(P$16=TRUE(),IF(P$41>0,EDATE(P$37,IF(sensi=1,IF(AND(P$21=1,$I$21),0,P$41+Dashboard!$Y$139),P$41))-1,P$37-1),) -> #VALUE!
C44: Operating duration - lenders | K44: years | M44: =YEARFRAC(M30,M43,1) -> #VALUE! | N44: =YEARFRAC(N30,N43,1) -> 0 | O44: =YEARFRAC(O30,O43,1) -> #VALUE! | P44: =YEARFRAC(P30,P43,1) -> #VALUE!
C46: Operating start - lenders | K46: date | M46: =IF(M14=TRUE(),M26+1,) -> 46107 | N46: =IF(N14=TRUE(),N26+1,) -> 0 | O46: =IF(O14=TRUE(),O26+1,) -> 46173 | P46: =IF(P14=TRUE(),P26+1,) -> 46173
C47: Operating end - lenders | K47: date | M47: =IF(M$14=TRUE(),EDATE(M46,M31+M35+M41)-1,) -> #VALUE! | N47: =IF(N$14=TRUE(),EDATE(N46,N31+N35+N41)-1,) -> 0 | O47: =IF(O$14=TRUE(),EDATE(O46,O31+O35+O41)-1,) -> #VALUE! | P47: =IF(P$14=TRUE(),EDATE(P46,P31+P35+P41)-1,) -> #VALUE!
C48: ref Perimeter (senior facility) | K48: ref | M48: =IFERROR(INDEX(#REF!,,MATCH(M2,#REF!,0)),0) -> 0 | N48: =IFERROR(INDEX(#REF!,,MATCH(N2,#REF!,0)),0) -> 0 | O48: =IFERROR(INDEX(#REF!,,MATCH(O2,#REF!,0)),0) -> 0 | P48: =IFERROR(INDEX(#REF!,,MATCH(P2,#REF!,0)),0) -> 0
B50: =B18+1 -> 3 | C50: PRODUCTION
C52: SELF-CONSUMPTION
A53: ASSET_SELF_CONSUMPTION | C53: Activation | K53: VRAI/FAUX | M53: FAUX | N53: FAUX | O53: FAUX | P53: VRAI
A54: ASSET_SELF_CONSUMPTION_ANNUAL_FEE | C54: Annual fee charged for self-consumption | K54: k€ / year | M54: 42 | N54: 43 | O54: 54 | P54: 1
C55: Annual fee charged for self-consumption | K55: k€ / year | M55: =IF(M$16=TRUE(),M54*M53,) -> #VALUE! | N55: =IF(N$16=TRUE(),N54*N53,) -> 0 | O55: =IF(O$16=TRUE(),O54*O53,) -> #VALUE! | P55: =IF(P$16=TRUE(),P54*P53,) -> #VALUE!
C56: Index | G56: list | I56: IPC
C58: CAPACITY
A59: ASSET_INSTALLED_CAPACITY | C59: Capacity @ COD | K59: kWc | M59: 159.705 | N59: 99.9 | O59: 31.05 | P59: 31.05
C60: Installed capacity | K60: kW | M60: =IF(AND(M$16=TRUE(),IF($I$22,M22=0,TRUE())),M59,) -> 159.705 | N60: =IF(AND(N$16=TRUE(),IF($I$22,N22=0,TRUE())),N59,) -> 0 | O60: =IF(AND(O$16=TRUE(),IF($I$22,O22=0,TRUE())),O59,) -> 31.05 | P60: =IF(AND(P$16=TRUE(),IF($I$22,P22=0,TRUE())),P59,) -> 31.05
C62: CAPACITY DEGRADATION
A63: ASSET_CAPACITY_DEGRADATION_RATE_LENDERS | C63: Degradation - lenders | K63: % | M63: 0.004 | N63: 0.004 | O63: 0.004 | P63: 0.004
A64: ASSET_CAPACITY_DEGRADATION_RATE_SPONSOR | C64: Degradation - sponsor | K64: % | M64: 0.004 | N64: 0.004 | O64: 0.004 | P64: 0.004
C65: Degradation | K65: % | M65: =INDEX(M63:M64,scenario,) -> #REF! | N65: =INDEX(N63:N64,scenario,) -> #REF! | O65: =INDEX(O63:O64,scenario,) -> #REF! | P65: =INDEX(P63:P64,scenario,) -> #REF!
A66: ASSET_CAPACITY_DEGRADATION_START_DATE | C66: Start date | K66: date | M66: =M30 -> 46107 | N66: =N30 -> 0 | O66: =O30 -> 46173 | P66: =P30 -> 46173
C67: Capacity at start date | K67: % | M67: =(1-M65)^YEARFRAC(M26,M66,1) -> #REF! | N67: =(1-N65)^YEARFRAC(N26,N66,1) -> #REF! | O67: =(1-O65)^YEARFRAC(O26,O66,1) -> #REF! | P67: =(1-P65)^YEARFRAC(P26,P66,1) -> #REF!
C69: Yield
A70: ASSET_YIELD_LENDERS | C70: Yield - lenders | K70: list | M70: P90 | N70: P90 | O70: P90 | P70: P90
A71: ASSET_YIELD_SPONSOR | C71: Yield - sponsor | K71: list | M71: P50 | N71: P50 | O71: P50 | P71: P50
C72: Yield | K72: list | M72: =INDEX(M70:M71,scenario,) -> #REF! | N72: =INDEX(N70:N71,scenario,) -> #REF! | O72: =INDEX(O70:O71,scenario,) -> #REF! | P72: =INDEX(P70:P71,scenario,) -> #REF!
A74: ASSET_YIELD_PORTOFOLIO_EFFECT | C74: Portfolio effect on P90 | K74: % | M74: 0.005 | N74: 0.005 | O74: 0.005 | P74: 0.005
A76: ASSET_YIELD_EXCL_CAPACITY_P90 | C76: P90 | K76: hours | M76: 1287.8 | N76: 1338.56 | O76: 1100.74 | P76: 1100.74
A77: ASSET_YIELD_EXCL_CAPACITY_P50 | C77: P50 | K77: hours | M77: 1370 | N77: 1424 | O77: 1171 | P77: 1171
A78: ASSET_YIELD_EXCL_CAPACITY | C78: Yield excl availability | K78: hours | M78: =IF(M72=0,0,INDEX(M76:M77,MATCH(M72,$C$76:$C$77,0))*(1+M74*(M72="P90"))) -> #REF! | N78: =IF(N72=0,0,INDEX(N76:N77,MATCH(N72,$C$76:$C$77,0))*(1+N74*(N72="P90"))) -> #REF! | O78: =IF(O72=0,0,INDEX(O76:O77,MATCH(O72,$C$76:$C$77,0))*(1+O74*(O72="P90"))) -> #REF! | P78: =IF(P72=0,0,INDEX(P76:P77,MATCH(P72,$C$76:$C$77,0))*(1+P74*(P72="P90"))) -> #REF!
C80: AVAILABILITY
A81: ASSET_PRODUCTION_AVAILABILITY_LENDERS | C81: Availability - lenders | K81: % | M81: 0.99 | N81: 0.99 | O81: 0.99 | P81: 0.99
A82: ASSET_PRODUCTION_AVAILABILITY_SPONSOR | C82: Availability - sponsor | K82: % | M82: 0.99 | N82: 0.99 | O82: 0.99 | P82: 0.99
A83: ASSET_PRODUCTION_AVAILABILITY | C83: Availability | K83: % | M83: =INDEX(M81:M82,scenario,) -> #REF! | N83: =INDEX(N81:N82,scenario,) -> #REF! | O83: =INDEX(O81:O82,scenario,) -> #REF! | P83: =INDEX(P81:P82,scenario,) -> #REF!
B85: =+B50+1 -> 4 | C85: REVENUES
C87: CONTRACTED REVENUES
A88: ASSET_CONTRACTED_REVENUES_REF_TARIFF | C88: Reference tariff (indexed @ COD), excl. bonus | K88: € / MWh | M88: 115.09593 | N88: 117.80078 | O88: 124.28508 | P88: 124.28508
A89: ASSET_CONTRACTED_REVENUES_BONUS_TARIFF | C89: Bonus | K89: € / MWh | M89: 4 | N89: 2 | O89: 5 | P89: 7
A90: ASSET_CONTRACTED_REVENUES_MALUS_TARIFF | C90: Malus | K90: € / MWh | M90: 42 | N90: 12 | O90: 42 | P90: 42
A91: ASSET_CONTRACTED_REVENUES_MALUS_ACTIVATION | C91: Malus activation | K91: VRAI/FAUX | M91: VRAI | N91: VRAI | O91: FAUX | P91: FAUX
A93: ASSET_REVENUES_INFLATION | C93: Index | K93: list | M93: 20% IPC | N93: 20% IPC | O93: IPC | P93: 40% IPC
A95: ASSET_CONTRACTED_REVENUES_YIELD_THRESHOLD_ACTIVATION | C95: Yield threshold activation | F95: ref_Typo | G95: SOL | H95: BAT | I95: OMBRIERE | K95: VRAI/FAUX | M95: VRAI | N95: VRAI | O95: VRAI | P95: VRAI
A96: ASSET_CONTRACTED_REVENUES_YIELD_THRESHOLD | C96: Yield threshold | F96: hours | G96: 1600 | H96: 1100 | I96: 1100 | K96: hours | M96: {=IFERROR(INDEX($G96:$I96,,MATCH(M$10,$G$95:$I$95,0)),0)} -> 1100 | N96: {=IFERROR(INDEX($G96:$I96,,MATCH(N$10,$G$95:$I$95,0)),0)} -> 1600 | O96: {=IFERROR(INDEX($G96:$I96,,MATCH(O$10,$G$95:$I$95,0)),0)} -> 1100 | P96: {=IFERROR(INDEX($G96:$I96,,MATCH(P$10,$G$95:$I$95,0)),0)} -> 1100
A97: ASSET_CONTRACTED_REVENUES_TARIFF_ABOVE_THRESHOLD | C97: Reference tariff above threshold | F97: € / MWh | G97: 50 | H97: 40 | I97: 40 | K97: € / MWh | M97: {=IFERROR(INDEX($G97:$I97,,MATCH(M$10,$G$95:$I$95,0)),0)} -> 40 | N97: {=IFERROR(INDEX($G97:$I97,,MATCH(N$10,$G$95:$I$95,0)),0)} -> 50 | O97: {=IFERROR(INDEX($G97:$I97,,MATCH(O$10,$G$95:$I$95,0)),0)} -> 40 | P97: {=IFERROR(INDEX($G97:$I97,,MATCH(P$10,$G$95:$I$95,0)),0)} -> 40
C98: Average tariff including yield threshold | K98: € / MWh | M98: =IF(M$16=TRUE(),IFERROR(((MAX(M$78*M$83-M$96,0)*M$97+MIN(M$96,M$78*M$83)*M$88)/(M$78*M$83))*M$95,0),) -> 0 | N98: =IF(N$16=TRUE(),IFERROR(((MAX(N$78*N$83-N$96,0)*N$97+MIN(N$96,N$78*N$83)*N$88)/(N$78*N$83))*N$95,0),) -> 0 | O98: =IF(O$16=TRUE(),IFERROR(((MAX(O$78*O$83-O$96,0)*O$97+MIN(O$96,O$78*O$83)*O$88)/(O$78*O$83))*O$95,0),) -> 0 | P98: =IF(P$16=TRUE(),IFERROR(((MAX(P$78*P$83-P$96,0)*P$97+MIN(P$96,P$78*P$83)*P$88)/(P$78*P$83))*P$95,0),) -> 0
C100: MARKET PRICES
C101: Merchant price scenario - lenders | M101: Mid captured | N101: Mid captured | O101: Mid captured | P101: Mid captured
C102: Merchant price scenario - sponsor | M102: Mid captured | N102: Mid captured | O102: Mid captured | P102: Mid captured
C103: Merchant price @Vehicle | M103: =IF(M16,IF(INDEX(#REF!,,M9)=TRUE(),INDEX(#REF!,,M9),),) -> #VALUE! | N103: =IF(N16,IF(INDEX(#REF!,,N9)=TRUE(),INDEX(#REF!,,N9),),) -> 0 | O103: =IF(O16,IF(INDEX(#REF!,,O9)=TRUE(),INDEX(#REF!,,O9),),) -> #VALUE! | P103: =IF(P16,IF(INDEX(#REF!,,P9)=TRUE(),INDEX(#REF!,,P9),),) -> #VALUE!
A104: ASSET_REVENUES_MERCHANT_PRICE_SCENARIO | C104: Merchant price scenario | M104: Mid captured | N104: Low captured | O104: 50 €/MWh | P104: Low non indexed
A106: ASSET_REVENUES_INFLATION_YEAR_START | C106: Year of inflation start if activated | F106: Index | G106: list | K106: year
B108: =B85+1 -> 5 | C108: OPEX
C110: Inflation
C111: Year of inflation start | K111: year | M111: =MAX(YEAR(M$30),YEAR(Model_Start_Date)) -> 2026 | N111: =MAX(YEAR(N$30),YEAR(Model_Start_Date)) -> 2025 | O111: =MAX(YEAR(O$30),YEAR(Model_Start_Date)) -> 2026 | P111: =MAX(YEAR(P$30),YEAR(Model_Start_Date)) -> 2026
C112: Inflation scenario | K112: index | M112: =MATCH(M111,ass_Market!$C$12:$C$63,0) -> 2 | N112: =MATCH(N111,ass_Market!$C$12:$C$63,0) -> 1 | O112: =MATCH(O111,ass_Market!$C$12:$C$63,0) -> 2 | P112: =MATCH(P111,ass_Market!$C$12:$C$63,0) -> 2
C113: {=TRANSPOSE(ass_Market!$W$9:$AC$9)} -> IPC | D113: ref | F113: =MATCH($C113,ass_Market!$W$9:$AC$9,0) -> 1 | K113: % | M113: {=IF(M$16,INDEX(ass_Market!$W$12:$AC$63,M$112,$F113),1)} -> 1.02 | N113: {=IF(N$16,INDEX(ass_Market!$W$12:$AC$63,N$112,$F113),1)} -> 1 | O113: {=IF(O$16,INDEX(ass_Market!$W$12:$AC$63,O$112,$F113),1)} -> 1.02 | P113: {=IF(P$16,INDEX(ass_Market!$W$12:$AC$63,P$112,$F113),1)} -> 1.02
C114: 20% IPC | D114: ref | F114: =MATCH($C114,ass_Market!$W$9:$AC$9,0) -> 2 | K114: % | M114: {=IF(M$16,INDEX(ass_Market!$W$12:$AC$63,M$112,$F114),1)} -> 1.004 | N114: {=IF(N$16,INDEX(ass_Market!$W$12:$AC$63,N$112,$F114),1)} -> 1 | O114: {=IF(O$16,INDEX(ass_Market!$W$12:$AC$63,O$112,$F114),1)} -> 1.004 | P114: {=IF(P$16,INDEX(ass_Market!$W$12:$AC$63,P$112,$F114),1)} -> 1.004
C115: 30% IPC | D115: ref | F115: =MATCH($C115,ass_Market!$W$9:$AC$9,0) -> 3 | K115: % | M115: {=IF(M$16,INDEX(ass_Market!$W$12:$AC$63,M$112,$F115),1)} -> 1.006 | N115: {=IF(N$16,INDEX(ass_Market!$W$12:$AC$63,N$112,$F115),1)} -> 1 | O115: {=IF(O$16,INDEX(ass_Market!$W$12:$AC$63,O$112,$F115),1)} -> 1.006 | P115: {=IF(P$16,INDEX(ass_Market!$W$12:$AC$63,P$112,$F115),1)} -> 1.006
C116: 40% IPC | D116: ref | F116: =MATCH($C116,ass_Market!$W$9:$AC$9,0) -> 4 | K116: % | M116: {=IF(M$16,INDEX(ass_Market!$W$12:$AC$63,M$112,$F116),1)} -> 1.008 | N116: {=IF(N$16,INDEX(ass_Market!$W$12:$AC$63,N$112,$F116),1)} -> 1 | O116: {=IF(O$16,INDEX(ass_Market!$W$12:$AC$63,O$112,$F116),1)} -> 1.008 | P116: {=IF(P$16,INDEX(ass_Market!$W$12:$AC$63,P$112,$F116),1)} -> 1.008
C117: 0 | D117: ref | F117: =MATCH($C117,ass_Market!$W$9:$AC$9,0) -> 5 | K117: % | M117: {=IF(M$16,INDEX(ass_Market!$W$12:$AC$63,M$112,$F117),1)} -> 1 | N117: {=IF(N$16,INDEX(ass_Market!$W$12:$AC$63,N$112,$F117),1)} -> 1 | O117: {=IF(O$16,INDEX(ass_Market!$W$12:$AC$63,O$112,$F117),1)} -> 1 | P117: {=IF(P$16,INDEX(ass_Market!$W$12:$AC$63,P$112,$F117),1)} -> 1
C118: 0 | D118: ref | F118: =MATCH($C118,ass_Market!$W$9:$AC$9,0) -> 5 | K118: % | M118: {=IF(M$16,INDEX(ass_Market!$W$12:$AC$63,M$112,$F118),1)} -> 1 | N118: {=IF(N$16,INDEX(ass_Market!$W$12:$AC$63,N$112,$F118),1)} -> 1 | O118: {=IF(O$16,INDEX(ass_Market!$W$12:$AC$63,O$112,$F118),1)} -> 1 | P118: {=IF(P$16,INDEX(ass_Market!$W$12:$AC$63,P$112,$F118),1)} -> 1
C119: 0 | D119: ref | F119: =MATCH($C119,ass_Market!$W$9:$AC$9,0) -> 5 | K119: % | M119: {=IF(M$16,INDEX(ass_Market!$W$12:$AC$63,M$112,$F119),1)} -> 1 | N119: {=IF(N$16,INDEX(ass_Market!$W$12:$AC$63,N$112,$F119),1)} -> 1 | O119: {=IF(O$16,INDEX(ass_Market!$W$12:$AC$63,O$112,$F119),1)} -> 1 | P119: {=IF(P$16,INDEX(ass_Market!$W$12:$AC$63,P$112,$F119),1)} -> 1
A122: ASSET_OPEX | C122: Opex value
B124: 1 | C124: OPEX €/MWh (period 1)
C125: Opex | K125: €/MWh | M125: 1 | O125: 2 | P125: 3
C126: Index | G126: list | I126: IPC | K126: €/MWh | M126: {=IFERROR(M125*IF(AND($I$22,M22=1),0,1)/INDEX(M$113:M$119,$I$127,),0)} -> 0.99206349 | N126: {=IFERROR(N125*IF(AND($I$22,N22=1),0,1)/INDEX(N$113:N$119,$I$127,),0)} -> 0 | O126: {=IFERROR(O125*IF(AND($I$22,O22=1),0,1)/INDEX(O$113:O$119,$I$127,),0)} -> 1.984127 | P126: {=IFERROR(P125*IF(AND($I$22,P22=1),0,1)/INDEX(P$113:P$119,$I$127,),0)} -> 2.9761905
C127: Start date | G127: ref | I127: 4 | K127: date | M127: =M$30 -> 46107 | N127: =N$30 -> 0 | O127: =O$30 -> 46173 | P127: =P$30 -> 46173
C128: End date | K128: date | M128: =M$39 -> 55458 | N128: =N$39 -> 0 | O128: =O$39 -> 55524 | P128: =P$39 -> 55524
...
